Workbook

Sheet Perfiles 
C2: PERFILES RAYENTUÉ
C4: FECHA ACTUALIZACIÓN | D4: 45199
C7: RESPONSABLE | D7: CHRISTIAN NUÑEZ BERRIOS- (13-05-2025)
B8: AÑO | C8: CONCURSO O LINEA | D8: CRI | E8: TÍTULO | F8: Programas Nacionales | G8: Investigador/a Encargado/a | H8: Ejecutor Principal | I8: ID- Perfil | J8: Estado Perfil | K8: Postulado | L8: Adjudicado | M8: Comentarios
B9: 44428 | C9: FIA Asignacion Directa | D9: 16-Rayentue | E9: Desarrollo de soluciones técnicas de manejo sustentable de suelos, agua y cultivos, para mejorar la situación post incendios forestales en predios de agricultores del área de secano de la región de O`Higgins y mitigar la problemática del cambio climático | F9: Agrosistemas Sustentables | G9: CARRASCO JIMENEZ JORGE | H9: INIA | I9: Sin Información | J9: Adjudicado | K9: SI | L9: Si
B10: 44414 | C10: FONTAGRO | D10: 16-Rayentue | E10: Agtechmetro | F10: Agrosistemas Sustentables | G10: FELMER ECHEVERRIA, SOFIA | H10: U. AUSTRAL | I10: Sin Información | J10: N/A | K10: SI | L10: RECHAZADO
B11: 43924 | C11: Súmate a Innovar - INNOVA-CORFO | D11: 16-Rayentue | E11: Efecto de la humidificación durante la cosecha de paltas para mejorar la condición de la fruta post-frío | F11: Producción Vegetal | G11: OTAROLA ALIAGA, JAIME IGNACIO | H11: INIA | I11: Sin Información | J11: Perfil Seleccionado | K11: NO | L11: NO APLICA | M11: No se realiza postulación porque la empresa interesada no puede realizar el aporte por la situación económica causada por COVID-19
B12: 43776 | C12: Anillos de Investigacion en Ciencia Y tecnolog a para la Regi n de O Higgins 2019 | D12: 16-RAYENTUE, 20-QUILAMAPU, 13-LA CRUZ | E12: Deep insight in the cherry plant defense responses tobacterial canker disease in a scenario of water restriction | F12: Producción Vegetal | G12: SAGREDO DIAZ, BORIS | H12: UOH | I12: Sin Información | J12: Perfil Seleccionado | K12: SI | L12: NO APLICA
B13: 43776 | C13: X Concurso de Equipamiento Cientifico y Tecnologico FONDEQUIP Regi n de O Higgins a o 2019 | D13: 16-RAYENTUE, 20-QUILAMAPU, 13-LA CRUZ | E13: Desarrollo de una plataforma de análisis de fragmentos y secuencias de ADN para fortalecer el desarrollo científico y tecnológico de la Región de O Higgins | F13: Producción Vegetal | G13: SAGREDO DIAZ, BORIS | H13: INIA | I13: Sin Información | J13: Perfil no Seleccionado | K13: SI | L13: NO APLICA
A14: 1 | B14: 43775 | C14: X Concurso de Equipamiento Cient fico y Tecnol gico FONDEQUIP Regi n de O Higgins a o 2019 | D14: 16-Rayentue | E14: Fortalecimiento y ampliación de un laboratorio de física de suelos y riego para su consolidación en la investigación y servicios en la región de O Higgins | F14: Agrosistemas Sustentables | G14: CARRASCO JIMENEZ JORGE | H14: INIA | I14: Sin Información | J14: En revisión por SubDirector Regional de I+D | K14: NO | L14: NO APLICA
B15: 43731 | C15: Convocatoria Nacional Proyectos de Innovación 2019 FIA | D15: 10-La Platina, 16-Rayentue, 20-Quilamapu, 30-Carillanca | E15: Conociendo la dinámica poblacional de Pseudomonas syringae para un control mas efectivo y sustentable del cáncer bacterial en Cerezos en Chile | F15: Producción Vegetal | G15: SAGREDO DIAZ, BORIS | H15: INIA | I15: Sin Información | J15: Perfil no Seleccionado | K15: NO | L15: NO APLICA
A16: 1 | B16: 43731 | C16: Convocatoria Nacional Proyectos de Innovación 2019 FIA | D16: 16-Rayentue, 20-Quilamapu | E16: Bioinmunizador microbiano endófito para el manejo agroecológico de la cebolla como estrategia para disminuir el uso de agroquímicos en el cultivo. | F16: Agrosistemas Sustentables | G16: VEGA CANDIA, BARBARA CHANTAL | H16: INIA | I16: Sin Información | J16: Perfil Seleccionado | K16: SI | L16: RECHAZADO | M16: NO APARECE EN LA LISTA DE PROYECTOS QUE PASARON LA 1° ETAPA
A17: 2 | B17: 43724 | C17: Convocatoria Nacional Proyectos de Innovación 2019 FIA | D17: 16-Rayentue | E17: Manejos sustentables para enfrentar un escenario de sequía en huertos frutales | F17: Producción Vegetal | G17: OTAROLA ALIAGA, JAIME IGNACIO | H17: INIA | I17: Sin Información | J17: Perfil no Seleccionado | K17: NO | L17: NO APLICA
A18: 3 | B18: 43711 | C18: FONDECYT DE POSTDOCTORADO 2020 | D18: 16-Rayentue, 15-Hidango, 20-Quilamapu, 14-Los Tilos | E18: DETERMINACIÓN DE LAS BASES FISIOLÓGICAS DE LA ADAPTACIÓN DE GENOTIPOS DE TRIGO CANDEAL DE INIA A CONDICIONES DE SEQUÍA EN EL SECANO MEDITERRÁNEO DE CHILE | F18: Producción Vegetal | G18: ALFARO JARA, CHRISTIAN EUGENIO | H18: INIA | I18: Sin Información | J18: Perfil Seleccionado | K18: SI | L18: NO APLICA
A19: 4 | B19: 43711 | C19: VIII Concurso de Investigación Tecnológica 2019-IDeA | D19: 16-Rayentue | E19: Validación de la tecnología de nanoburbujas en distintos niveles de la cadena de producción de fruta fresca | F19: Producción Vegetal | G19: OTAROLA ALIAGA, JAIME IGNACIO | H19: INIA | I19: Sin Información | J19: Perfil Seleccionado | K19: SI | L19: NO APLICA
A20: 5 | B20: 43711 | C20: VIII Concurso de Investigación Tecnológica 2019-IDeA | D20: 10-La Platina, 16-Rayentue, 20-Quilamapu, 30-Carillanca | E20: Nuevas herramientas de monitoreo de poblaciones de Pseudomonas syringae agente causal del cáncer bacterial en cerezos para apoyar sistemas integrados de control y reducir contaminación con Cu+2. | F20: Producción Vegetal | G20: SAGREDO DIAZ, BORIS | H20: INIA | I20: Sin Información | J20: Perfil Seleccionado | K20: SI | L20: NO APLICA
A21: 6 | B21: 43685 | C21: Bienes Públicos 2019- Temática "Adaptación al Cambio Climático" | D21: 16-Rayentue | E21: Adaptación al manejo agronómico del cultivo de cerezo desarrollado bajo cubiertas plásticas | F21: Producción Vegetal | G21: OTAROLA ALIAGA, JAIME IGNACIO | H21: INIA | I21: Sin Información | J21: Perfil Seleccionado | K21: SI | L21: NO APLICA | M21: No es pertinente
A22: 7 | B22: 43681 | C22: Bienes Públicos 2019- Temática "Adaptación al Cambio Climático" | D22: 16-Rayentue | E22: Manejo de frutales ante un escenario de sequía en la región de O’Higgins | F22: Producción Vegetal | G22: OTAROLA ALIAGA, JAIME IGNACIO | H22: INIA | I22: Sin Información | J22: En revisión por SubDirector Regional de I+D | K22: NO | L22: NO APLICA
A23: 8 | B23: 43677 | C23: Bienes Públicos 2019- Temática "Adaptación al Cambio Climático" | D23: 16-Rayentue | E23: Generación de una línea base para el establecimiento frutal en el valle de Nilahue con disponibilidad de agua de riego a través del embalse Convento Viejo. | F23: Producción Vegetal | G23: OTAROLA ALIAGA, JAIME IGNACIO | H23: INIA | I23: Sin Información | J23: En revisión por SubDirector Regional de I+D | K23: NO | L23: NO APLICA
A24: 9 | B24: 43656 | C24: Concurso Postdoctorado 2019 | D24: Rayentué | E24: INTERACCIÓN G X E DE CARACTERES DE ADAPTACIÓN A CONDICIONES DE ESTRÉS HÍDRICO EN Y SU EFECTO SOBRE LA DETERMINACIÓN DEL RENDIMIENTO EN TRIGO CANDEAL | F24: Producción Vegetal | G24: ALFARO JARA, CHRISTIAN EUGENIO | H24: INIA | I24: Sin Información | J24: Perfil Seleccionado | K24: SI | L24: RECHAZADO
A25: 10 | B25: 43656 | C25: Concurso Regular Fondecyt 2019 | D25: Rayentué | E25: MECANISMOS HIDRAULICOS Y DE METABOLISMO DEL CARBONO EN LA ADAPTACION DEL CULTIVO DE TRIGO A CONDICIONES DE CAMBIO CLIMÁTICO EN AMBIENTES DE SEQUIA SEVERA DE TIPO MEDITERRANEO | F25: Producción Vegetal | G25: ALFARO JARA, CHRISTIAN EUGENIO | H25: INIA | I25: Sin Información | J25: Perfil Seleccionado | K25: NO | L25: NO APLICA
A26: 11 | B26: 43642 | C26: XXIII Concurso Nacional de Proyectos Explora para elaboración de productos de divulgación de las ciencias y la tecnología 2019 2020 | D26: 16-RAYENTUE, 15-HIDANGO | E26: NATIVOAPP 2 0 Plataforma móvil y web para mapear e identificarflora nativa en Chile | F26: Producción Vegetal | G26: SAGREDO DIAZ, BORIS | H26: INIA | I26: Sin Información | J26: APROBADO | K26: SI | L26: RECHAZADO | M26: no adjudicar la propuesta, debido a que la solución no está debidamente identiﬁcada
A27: 12 | B27: 43628 | C27: IX Concurso de Vinculación Ciencia Empresa | D27: 16-RAYENTUE, 01-DIRECCIÓN NACIONAL | E27: Vinculación Ciencia Empresa Una Plataforma Científico Técnica para enfrentar los desafíos ante el aumento de cobertura de riego del ECV Embalse Convento Viejo en la comuna de Marchigue | F27: Producción Vegetal | G27: SAGREDO DIAZ, BORIS | H27: INIA | I27: Sin Información | J27: APROBADO | K27: NO | L27: NO APLICA | M27: No alcanzo a presentarlo a la FF
A28: 13 | B28: 43620 | C28: Concurso Regular Fondecyt 2020 | D28: 14-LOS TILOS, 16-RAYENTUE, 10-LA PLATINA, 05-INTIHUASI | E28: Disentangling the epigenetic influence on fruit development and ripening in three stone fruits Prunus species | F28: Producción Vegetal | G28: DONOSO CONTRERAS, JOSE MANUEL | H28: U. de Chile | I28: Sin Información | J28: APROBADO | K28: SI | L28: APROBADO
A29: 14 | B29: 43616 | C29: PCI ECOS CONICYT Concurso de proyectos de intercambio Chile Francia 2019 | D29: 14-LOS TILOS, 10-LA PLATINA, 16-RAYENTUE | E29: Collaborative counter season research efforts between France and Chile analysis of traits affected by climate change in sweet cherry in order to create new varieties adapted to future environmental conditions | F29: Producción Vegetal | G29: DONOSO CONTRERAS, JOSE MANUEL | H29: INIA | I29: Sin Información | J29: APROBADO | K29: SI | L29: RECHAZADO
A30: 1 | B30: 43493 | C30: CONCURSO IDEA I+D 2019 | D30: 16-RAYENTUE, 20-QUILAMAPU | E30: Plataforma de Información Epidemiologica para facilitar el control del Cáncer Bacterial en Cerezos | F30: Producción Vegetal | G30: SAGREDO DIAZ, BORIS | H30: INIA | I30: Sin Información | J30: APROBADO | K30: SI | L30: RECHAZADO
A31: 2 | B31: 43291 | C31: Septimo Concurso de Investigaci n Tecnol gica 2018 IDeA | D31: Rayentué | E31: Plataforma de Información Epidemiologica para facilitar el control del Cáncer Bacterial en Cerezos | F31: Producción Vegetal | G31: SAGREDO DIAZ, BORIS | H31: INIA | I31: Sin Información | J31: Perfil Seleccionado | K31: NO | L31: NO APLICA | M31: NO SE ALCANZO A POSTULAR
A32: 3 | B32: 43291 | C32: Otros Concursos de alcance nacional o regional 2018 | D32: Rayentué | E32: Identificación de marcadores moleculares asociados a la determinación del sexo en maqui A chilensis y su ubicación a nivel cromosómico | F32: Producción Vegetal | G32: SAGREDO DIAZ, BORIS | H32: INIA | I32: Sin Información | J32: En revisión por SubDirector Regional de I+D | K32: SI | L32: RECHAZADO
A33: 4 | B33: 43291 | C33: Otros Concursos de alcance nacional o regional 2018 | D33: Rayentué | E33: Plataforma de Información Epidemiologica para facilitar el control del Cáncer Bacterial en Cerezos | F33: Producción Vegetal | G33: SAGREDO DIAZ, BORIS | H33: INIA | I33: Sin Información | J33: En revisión por SubDirector Regional de I+D | K33: NO | L33: NO APLICA | M33: NO SE ALCANZO A POSTULAR
A34: 5 | B34: 43291 | C34: FIA-Convocatoria Nacional Giras Nacionales para la Innovaci n de la Peque a Agricultura 2018 | D34: Rayentué | E34: Adquisición de conocimientos en el control biológico de plagas y enfermedades en las principales hortalizas de la región de O higgins | F34: Agrosistemas Sustentables | G34: VEGA CANDIA, BARBARA CHANTAL | H34: INIA | I34: Sin Información | J34: Perfil Seleccionado | K34: SI | L34: RECHAZADO
A35: 6 | B35: 43291 | C35: Otros Concursos de alcance nacional o regional 2018 | D35: Rayentué | E35: Captura de conocimientos y experiencias en el manejo sustentable del cultivo del tomate | F35: Agrosistemas Sustentables | G35: VEGA CANDIA, BARBARA CHANTAL | H35: INIA | I35: Sin Información | J35: En corrección por Comisión de Evaluación Nacional | K35: SI | L35: RECHAZADO
A36: 7 | B36: 46126 | C36: Fondecyt de Iniciación en Investigación 2027 | D36: 16-Rayentué | E36: Predictive physiological traits for robust quinoa selection across dynamic drought-prone Mediterranean environments | F36: Programa Nacional de Producción Vegetal | G36: ESTRADA BRAVO, FELIX RODOLFO | H36: INIA | I36: 1659 | J36: Seleccionado con condiciones | M36: En concurso
A37: 8 | B37: 46056 | C37: XVII Concurso Fondo de Investigación del Bosque Nativo-CONAF 2026 | D37: 16-Rayentué | E37: Restauración de bosques fragmentados del secano costero de la Región de O’Higgins mediante el uso de especies nodrizas leñosas y cactáceas nativas | F37: Programa Nacional de Agrosistemas Sustentables | G37: CACERES CELEDON, EMILIO JOSE | H37: INIA | I37: 1617 | J37: Postulado | K37: Si | M37: En concurso
A38: 9 | B38: 46051 | C38: Concurso de Investigación Tecnológica IDeA 2026 | D38: 16-Rayentué | E38: Hacia un control mas sustentable del cáncer bacterial en cerezos: reducción del uso de cobre y pérdidas productivas mediante herramientas biotecnológicas y monitoreo molecular predictivo | F38: Programa Nacional de Producción Vegetal | G38: SAGREDO DIAZ, BORIS | H38: INIA | I38: 1615 | J38: Postulado | K38: Si | M38: En concurso
A39: 10 | B39: 45944 | C39: Viraliza Eventos 2025 | D39: Rayentué | E39: Viraliza Agro Tech O’Higgins (Viraliza Eventos 2025) | F39: Programa Nacional de Agrosistemas Sustentables | G39: AGUIRRE AGUILERA, CRISTIAN | H39: UOH - Universidad de O'Higgins | I39: 1553 | J39: Postulado | K39: Si | L39: Si | M39: En concurso
A40: 11 | B40: 45901 | C40: Consultorías Regionales para la Innovación 2025 | D40: Rayentué | E40: Gestión eficiente del agua de riego de Convento Viejo 2: diagnóstico de suelos, riego y cultivos en las comunas de Lolol, Pumanque y Marchigue | F40: Programa Nacional de Agrosistemas Sustentables | G40: CACERES CELEDON, EMILIO JOSE | H40: INIA | I40: 1523 | J40: Postulado | K40: Si | L40: Si | M40: En concurso
A41: 12 | B41: 45901 | C41: Giras nacionales de innovación para Mujeres Agroinnovadoras 2025 | D41: Rayentué | E41: Raíces femeninas: Gira agroecológica de mujeres transformadoras | F41: Programa Nacional de Agrosistemas Sustentables | G41: VEGA CANDIA, BARBARA CHANTAL | H41: INIA | I41: 1522 | J41: Postulado | K41: Si | L41: No | M41: En concurso
B42: 45886 | C42: Startup Ciencia 2026 | D42: Rayentué | E42: Optiriego Plus: Aceleramiento del desarrollo tecnológico y comercial del sensor Optiriego para optimizar el manejo del riego en uva vinífera (Startup Ciencia 2026) | F42: Programa Nacional de Producción Vegetal | G42: MARTINEZ CASTILLO, JUAN PABLO | H42: YUMMY TECH LIMITADA | I42: 1472 | J42: Postulado | K42: Si | M42: En concurso
B43: 45874 | C43: IDeA I+D 2026 | D43: Rayentué | E43: Desarrollo y validación de modelos de predicción genómica en cerezo para una selección anticipada y precisa de nuevas variedades | F43: Programa Nacional de Producción Vegetal | G43: DONOSO CONTRERAS, JOSE MANUEL | H43: UCHILE - Universidad de Chile | I43: 1467 | J43: Postulado | K43: Si | M43: En concurso
A44: 13 | B44: 45860 | C44: Convocatoria Nacional Proyectos de Innovación para el Agro 2025-2026 FIA-Propuesta completa | D44: Rayentué | E44: Herramienta digital para la inspección de pulverizadores hidroneumáticos utilizados en huertos frutales | F44: Programa Nacional de Producción Vegetal | G44: ABARCA REYES, LUIS PATRICIO | H44: INIA | I44: 1444 | J44: Postulado | K44: Si | L44: No | M44: En concurso
A45: 1 | B45: 45860 | C45: Convocatoria Nacional Proyectos de Innovación para el Agro 2025-2026 FIA-Propuesta completa | D45: Rayentué | E45: Cuaderno de campo digital para chequeo de inspecciones y regulaciones de pulverizadores hidroneumáticos utilizado en frutales | F45: Programa Nacional de Producción Vegetal | G45: NUÑEZ BERRIOS, CHRISTIAN ESTEBAN | H45: INIA | I45: 1443 | J45: Rechazado | K45: No | L45: NO APLICA | M45: Perfil ingresado por error
A46: 2 | B46: 45860 | C46: Convocatoria Nacional Proyectos de Innovación para el Agro 2025-2026 FIA-Propuesta completa | D46: Rayentué | E46: Gestión sostenible del rendimiento y calidad del trigo en el secano interior de sequía severa en la Región de O'Higgins, aumentando la EUA y EUN. | F46: Programa Nacional de Producción Vegetal | G46: RUBILAR TORRES, FELIPE ANDRES | H46: UCHILE - Universidad de Chile | I46: 1412 | J46: Postulado | K46: Si | L46: No | M46: En concurso
A47: 3 | B47: 45860 | C47: Convocatoria Nacional Proyectos de Innovación para el Agro 2025-2026 FIA-Propuesta completa | D47: Rayentué | E47: Optimización del manejo y diseño de invernaderos hortícolas mediante una plataforma de monitoreo ambiental en la Región de O’Higgins | F47: Programa Nacional de Producción Vegetal | G47: MARTINEZ CASTILLO, JUAN PABLO | H47: INIA | I47: 1395 | J47: Postulado | K47: Si | L47: No | M47: En concurso
A48: 4 | B48: 45860 | C48: Convocatoria Nacional Proyectos de Innovación para el Agro 2025-2026 FIA-Propuesta completa | D48: Rayentué | E48: Estrategias para mitigar el daño por piel de lagarto en cerezas de exportación | F48: Programa Nacional de Producción Vegetal | G48: DONOSO CONTRERAS, JOSE MANUEL | H48: INIA | I48: 1388 | J48: Postulado | K48: Si | L48: Si | M48: En concurso
A49: 5 | B49: 45860 | C49: Convocatoria Nacional Proyectos de Innovación para el Agro 2025-2026 FIA-Propuesta completa | D49: Rayentué | E49: Validación de un modelo de alerta preventiva contra los principales hongos de madera que afectan al cultivo del cerezo para mantener los estándares de calidad y competitividad en el mercado | F49: Programa Nacional de Producción Vegetal | G49: OTAROLA ALIAGA, JAIME IGNACIO | H49: INIA | I49: 1387 | J49: Postulado | K49: Si | L49: Si | M49: En concurso
A50: 6 | B50: 45832 | C50: Fondecyt Regular 2026 | D50: Rayentué | E50: Disentangling the epigenetic influence on differentiation of fruit development between early and late varieties in sweet cherry (Prunus avium) | F50: Programa Nacional de Producción Vegetal | G50: DONOSO CONTRERAS, JOSE MANUEL | H50: UCHILE - Universidad de Chile | I50: 1363 | J50: Postulado | K50: Si | L50: NO APLICA | M50: En concurso
A51: 7 | B51: 45832 | C51: Fondecyt Regular 2026 | D51: Rayentué | E51: Improving salinity tolerance in ‘Old Limachino Tomato’ through grafting onto two clonal rootstocks derived from reciprocal interspecific crosses between cultivated and wild tomato genotypes | F51: Programa Nacional de Producción Vegetal | G51: MARTINEZ CASTILLO, JUAN PABLO | H51: INIA | I51: 1362 | J51: Postulado | K51: Si | L51: NO APLICA | M51: En concurso
A52: 8 | B52: 45768 | C52: Crea y Valida 2025 | D52: Rayentué | E52: Sensor Optiriego: Mejoras de un prototipo comercial de sensor portátil para la toma de decisiones del riego en tomate y uva vinífera mediante el monitoreo de variables fisiológicas de la planta y ambiente. | F52: Programa Nacional de Producción Vegetal | G52: MARTINEZ CASTILLO, JUAN PABLO | H52: Yummy Tech Limitada | I52: 1316 | J52: No Postulado | K52: No | M52: Empresa desiste de la postulación
A53: 9 | B53: 45749 | C53: Fondecyt de Iniciación en Investigación 2026 | D53: 16-Rayentué | E53: Identification of stable and heritable physiological traits for the selection of drought-tolerant quinoa (Chenopodium quinoa Willd.) genotypes under drought environments | F53: Producción Vegetal | G53: ESTRADA BRAVO, FELIX RODOLFO | H53: INIA | I53: 1303 | J53: Postulado | K53: Si | M53: En evaluación CNE
A54: 10 | B54: 45708 | C54: Concurso de Investigación Tecnológica IDeA 2025 | D54: 16-Rayentué | E54: GENERANDO INFORMACIÓN CLAVE PARA EL DESARROLLO DE ESTRATEGIAS SUSTENTABLES DE CONTROL DEL CANCER BACTERIAL EN CEREZOS: BASADOS EN LAS CARACTERÍSTICAS DE LA POBLACIÓN DEL AGENTE CAUSAL | F54: Producción Vegetal | G54: SAGREDO DIAZ, BORIS | H54: INIA | I54: 1267 | J54: No Adjudicado | K54: Si
A55: 1 | B55: 45606 | C55: Convocatoria Nacional Proyectos de Innovación para el agro con Énfasis Regional 2024-2025 FIA | D55: 16-Rayentué | E55: Desarrollo de estrategias de riego deficitario controlado en diferentes variedades de cerezos y zonas agroclimáticas de Chile con baja disponibilidad hídrica. | F55: Programa Nacional de Agrosistemas Sustentables | G55: CACERES CELEDON, EMILIO JOSE | H55: INIA | I55: 1213 | J55: No Adjudicado | K55: Si | L55: No
A56: 2 | B56: 45606 | C56: Convocatoria Nacional Proyectos de Innovación para el agro con Énfasis Regional 2024-2025 FIA | D56: 16-Rayentué | E56: Empaquetamiento técnico y comercial de la primera variedad de cereza chilena para un mercado de alta exigencia en calidad | F56: Producción Vegetal | G56: OTAROLA ALIAGA, JAIME IGNACIO | H56: INIA | I56: 1209 | J56: Adjudicado | K56: Si
A57: 3 | B57: 45581 | C57: Fondo Regional para la Productividad y el Desarrollo (FRPD)- Región de O'Higgins 2024 | D57: 16-Rayentué | E57: Desarrollo de la agricultura urbana y periurbana como alternativa de desarrollo sostenible para la producción de alimentos en la Región de O`Higgins. | F57: Programa Nacional de Agrosistemas Sustentables | G57: RUBILAR TORRES, FELIPE ANDRES | H57: INIA | I57: 1165 | J57: Adjudicado | K57: Si | M57: PY en estado de validación de convenios
A58: 4 | B58: 45581 | C58: Fondo Regional para la Productividad y el Desarrollo (FRPD)- Región de O'Higgins 2024 | D58: 16-Rayentué | E58: OptiVol: Una plataforma digital para la optimización de la pulverización hidroneumática utilizada en frutales de hoja caduca | F58: Programa Nacional de Agrosistemas Sustentables | G58: ABARCA REYES, LUIS PATRICIO | H58: INIA | I58: 1164 | J58: No Postulado | K58: No
A59: 5 | B59: 45581 | C59: Fondo Regional para la Productividad y el Desarrollo (FRPD)- Región de O'Higgins 2024 | D59: 16-Rayentué | E59: Transferencia de un paquete tecnológico para el control de ataques de depredadores en ovinos del secano costero de O’Higgins. | F59: Programa Nacional de Producción Animal | G59: QUEZADA JARA, MARCELO | H59: INIA | I59: 1163 | J59: Adjudicado | K59: Si
A60: 6 | B60: 45576 | C60: Fondo Regional para la Productividad y el Desarrollo (FRPD)- Región de O'Higgins 2024 | D60: 16-Rayentué | E60: Transferencia del diagnóstico y manejo integrado de enfermedades del almendro: estrategias innovadoras para aumentar la competitividad del cultivo en la región de ohiggins | F60: Programa Nacional de Agrosistemas Sustentables | G60: Riquelme Toledo Danae | H60: INIA | I60: 1162 | J60: Adjudicado
A61: 7 | B61: 45576 | C61: Fondo Regional para la Productividad y el Desarrollo (FRPD)- Región de O'Higgins 2024 | D61: 16-Rayentué | E61: Biofábricas en la región de O´Higgins, una alternativa a la producción de agroinsumos con visión agroecológica | F61: Programa Nacional de Agrosistemas Sustentables | G61: VEGA CANDIA, BARBARA CHANTAL | H61: INIA | I61: 1158 | J61: No Adjudicado | K61: Si
A62: 8 | B62: 45576 | C62: Fondo Regional para la Productividad y el Desarrollo (FRPD)- Región de O'Higgins 2024 | D62: 16-Rayentué | E62: Sistema de detección y alerta en tiempo real para el control preventivo y oportuno de las principales enfermedades de madera que afectan a los frutales de carozo | F62: Programa Nacional de Agrosistemas Sustentables | G62: Atimira Passalacqua Fabiola | H62: INIA | I62: 1153 | J62: Adjudicado | K62: Si | M62: En concurso
A63: 9 | B63: 45509 | C63: Red de Fomento Sostenible-1º Convocatoria 2024-Sector Agricultura | D63: 16-Rayentué | E63: “RedFrutiT: Red de innovación tecnológica para una fruticultura sustentable y resiliente en Chile” (Red de Fomento Sostenible-1º Convocatoria 2024-Sector Agricultura) | F63: Producción Vegetal | G63: OTAROLA ALIAGA, JAIME IGNACIO | H63: UC DAVIS CHILE - FUNDACION UC DAVIS CHILE LIFE SCIENCES INNOVATION CENTER | I63: 1112 | J63: No Adjudicado | K63: Si | L63: No | M63: Se ha solicitado por correo los papeles a la ejecutora principal para cerrar el proceso ya que se sabe que no fue adjudicado
A64: 10 | B64: 45504 | C64: IDeA I+D 2025 | D64: 16-Rayentué | E64: Desarrollo de un sistema de producción de plantas de tomate injertadas sobre portainjertos clonales originados por cruzamientos interespecíficos (S. lycopersicum x S. chilense) para mejorar la productividad y calidad de tomate fresco. | F64: Producción Vegetal | G64: MARTINEZ CASTILLO, JUAN PABLO | H64: INIA | I64: 1109 | J64: Postulado | K64: Si
A65: 1 | B65: 45447 | C65: Fondecyt Regular 2025 | D65: 16-Rayentué | E65: Improving salt tolerance of “Old Limachino Tomato” by using two clonal rootstocks issued from interspecific reciprocal crosses between wild and cultivated tomato, with different level of salt tolerance. | F65: Producción Vegetal | G65: MARTINEZ CASTILLO, JUAN PABLO | H65: INIA | I65: 1046 | J65: No Adjudicado | K65: Si | L65: No
A66: 2 | B66: 45441 | C66: Fondecyt Regular 2025 | D66: 16-Rayentué | E66: Disentangling the epigenetic influence on differentiation of fruit development between early and late varieties in sweet cherry (Prunus avium) (FONDECYT REGULAR) | F66: Producción Vegetal | G66: DONOSO CONTRERAS, JOSE MANUEL | H66: INIA | I66: 1045 | J66: No Adjudicado | K66: Si | L66: No
A67: 3 | B67: 45437 | C67: Fondecyt Regular 2025 | D67: 16-Rayentué | E67: Understanding the genetics related to orange peel disorder in sweet cherry (Prunus avium L.) | F67: Producción Vegetal | G67: DONOSO CONTRERAS, JOSE MANUEL | H67: INIA | I67: 1043 | J67: No Adjudicado | K67: Si | L67: No
A68: 4 | B68: 45272 | C68: Crea y Valida Foco en Sostenibilidad 2023 | D68: 16-Rayentué | E68: Desarrollo de un agente antifúngico a partir de saponinas presentes en líneas avanzadas de quínoas chilenas | F68: Producción Vegetal | G68: ESTRADA BRAVO, FELIX RODOLFO | H68: TECNOLOGIA EN FENOMICA DE PLANTAS LIMITADA | I68: 890 | J68: No Seleccionado | K68: No
A69: 5 | B69: 45231 | C69: Concurso Startup Ciencia 2024 (2º llamado 2023) | D69: 16-Rayentué | E69: Desarrollo de un sensor portátil (Optiriego) que optimiza el manejo de riego en tomates y uva vinífera | F69: Producción Vegetal | G69: MARTINEZ CASTILLO, JUAN PABLO | H69: YUMMY FRUIT SPA | I69: 879 | J69: Adjudicado | K69: Si | L69: Si
A70: 6 | B70: 45200 | C70: Convocatoria Nacional FIA 2023-2024 "Proyectos de Innovación en Sistemas Alimentarios Sostenibles" | D70: 16-Rayentué | E70: Diversificación floral con especies nativas y cultivos tradicionales con riego tecnificado, mejorando la disponibilidad de alimento en Apis melífera. | F70: Agrosistemas Sustentables | G70: CACERES CELEDON, EMILIO JOSE | H70: INIA | I70: 846 | J70: No Adjudicado | K70: Si | L70: No | M70: Comunicación no pertinente 09-11-2023
A71: 7 | B71: 45108 | C71: FIC O'Higgins 2023 | D71: 16-Rayentué | E71: Desarrollo de soluciones técnicas para la recuperación de suelos y cultivos en terrenos afectados por desborde de ríos e inundaciones, en la pequeña y mediana agricultura en las comunas de Coltauco y San Vicente, Región de O’Higgins | F71: Agrosistemas Sustentables | G71: CARRASCO JIMENEZ JORGE | H71: INIA | I71: 792 | J71: No adjudicado | K71: Si | L71: No | M71: No admitido por bases (faltó documentación)
A72: 8 | B72: 45108 | C72: FIC O'Higgins 2023 | D72: 16-Rayentué | E72: Transferencia tecnológica y revalorización de vides criollas y productos derivados con tradición patrimonial campesina para la Región de O'Higgins | F72: Producción Vegetal | G72: SAGREDO DIAZ, BORIS | H72: INIA | I72: 790 | J72: Adjudicado | K72: Si | L72: Si | M72: Comunicación de adjudicación 14-11-2023
A73: 9 | B73: 45108 | C73: FIC O'Higgins 2023 | D73: 16-Rayentué | E73: Semillero colaborativo regional de variedades tradicionales INIA, en la comuna de San Vicente | F73: Producción Vegetal | G73: VEGA CANDIA, BARBARA CHANTAL | H73: INIA | I73: 789 | J73: No Adjudicado | K73: Si | L73: No
A74: 10 | B74: 45108 | C74: FIC O'Higgins 2023 | D74: 16-Rayentué | E74: Biofiltros domiciliarios para la utilización de aguas grises con riego tecnificado para la pequeña agricultura en las comunas de Pumanque, Navidad y Pichilemu | F74: Agrosistemas Sustentables | G74: CACERES CELEDON, EMILIO JOSE | H74: INIA | I74: 788 | J74: No Adjudicado | K74: Si | L74: No | M74: No admitido por bases (faltó documentación)
A75: 11 | B75: 45108 | C75: FONTAGRO 2023 | D75: 16-Rayentué | E75: Diversificación de productos funcionales de quinua para contribuir a la seguridad alimentaria | F75: Producción Vegetal | G75: ESTRADA BRAVO, FELIX RODOLFO | H75: UNAL - Universidad Nacional de Colombia- Colombia | I75: 785 | J75: No Adjudicado | K75: Si | L75: No
A76: 12 | B76: 45108 | C76: FIA | D76: 16-Rayentué | E76: Desarrollo de un potencial agente antifúngico a partir de saponinas presentes en líneas avanzadas de quínoa | F76: Producción Vegetal | G76: ESTRADA BRAVO, FELIX RODOLFO | H76: Tecnofen | I76: 755 | J76: No Adjudicado | K76: Si | L76: No
A77: 13 | B77: 45078 | C77: FONDECYT 2024 | D77: 16-Rayentué | E77: Disentangling the epigenetic influence on differentiation of fruit development between early and late varieties in sweet cherry (Prunus avium) | F77: Producción Vegetal | G77: DONOSO CONTRERAS, JOSE MANUEL | H77: Universidad de Chile | I77: 748 | J77: No Adjudicado | K77: Si | L77: No
A78: 14 | B78: 45047 | C78: Anillos de Investigación en Áreas Temáticas Específicas 2023 | D78: 16-Rayentué | E78: Plant Abiotic Stress tolerance for a Sustainable Agriculture (PASSA): Molecular Strategies for improving Plant Tolerance to drought and salinity | F78: Producción Vegetal | G78: MARTINEZ CASTILLO, JUAN PABLO | H78: Universidad de Chile | I78: 677 | J78: No Adjudicado | K78: Si | L78: No
A79: 15 | B79: 44987 | C79: Concurso de Investigación Tecnológica IDeA 2023 (apertura 2022) | D79: 16-Rayentué | E79: Validación en huertos comerciales de selecciones avanzadas de cerezos de distintos programas de mejoramiento genético de Chile y del extranjero | F79: Producción Vegetal | G79: DONOSO CONTRERAS, JOSE MANUEL | H79: Universidad de Talca | I79: 662 | J79: No Seleccionado | K79: NO | L79: NO
A80: 1 | B80: 45017 | C80: FONDECYT Iniciación 2024 | D80: 16-Rayentué | E80: A comprehensive characterization of physiological and agronomic traits for detecting keystones to select quinoa (Chenopodium quinoa Willd.) genotypes under adverse environments | F80: Producción Vegetal | G80: ESTRADA BRAVO, FELIX RODOLFO | H80: INIA | I80: 661 | J80: No Adjudicado | K80: Si | L80: No
A81: 2 | B81: 44835 | C81: FIA 2022-2023 | D81: 16-Rayentué | E81: Plataforma interactiva para el desarrollo de mejoras en el control de plagas en cultivo de cítricos a través de la pulverización hidroneumática | F81: Agrosistemas Sustentables | G81: ABARCA REYES, LUIS PATRICIO | H81: INIA | I81: 609 | J81: Adjudicado | K81: Si | L81: Si | M81: Aprobado
A82: 3 | B82: 44835 | C82: FIA 2022-2023 | D82: 16-Rayentué | E82: Caracterización y evaluación de suelos de predios de la pequeña agricultura para su incorporación a la producción de rubros de mayor rentabilidad como la fruticultura y horticultura | F82: Agrosistemas Sustentables | G82: CARRASCO JIMENEZ JORGE | H82: INIA | I82: 601 | J82: Perfil no Seleccionado | K82: No
A83: 4 | B83: 44835 | C83: FIA 2022-2023 | D83: 16-Rayentué | E83: Control y prevención de los incendios forestales con ovinos para mitigar los efectos del cambio climático. | F83: Producción Animal | G83: QUEZADA JARA, MARCELO | H83: INIA | I83: 595 | J83: Perfil no Seleccionado | K83: No
A84: 5 | B84: 44835 | C84: FIA 2022-2023 | D84: 16-Rayentué | E84: Nuevas estrategias de riego para el cultivo del nogal injertado sobre portainjertos clonales | F84: Producción Vegetal | G84: OTAROLA ALIAGA, JAIME IGNACIO | H84: INIA | I84: 593 | J84: Adjudicado | K84: Si | L84: Si | M84: Aprobado
A85: 6 | B85: 44774 | C85: FIC | D85: 16-Rayentué | E85: Transferencia de la caracterización y evaluación de suelos de predios de la pequeña agricultura para su incorporación a la producción de rubros de mayor rentabilidad como la fruticultura y horticultura | F85: Agrosistemas Sustentables | G85: CARRASCO JIMENEZ JORGE | H85: INIA | I85: 506 | J85: Seleccionado con condiciones | K85: No | M85: No postulado por imposibilidad de gestionar recursos pecuniarios de contrapartida en el monto que haga viable la propuesta.
A86: 7 | B86: 44774 | C86: FIC | D86: 16-Rayentué | E86: Optimización de la aplicación de biocontroladores de origen microbiano a través de diferentes técnicas de pulverización en cultivos agrícolas de importancia para la Región de O'Higgins | F86: Producción Vegetal | G86: ABARCA REYES, LUIS PATRICIO | H86: INIA | I86: 493 | J86: Adjudicado | K86: Si | L86: Si | M86: Aprobado
A87: 8 | B87: 44774 | C87: FIC | D87: 16-Rayentué | E87: Transferencia bioinmunizador endófito para el control de plagas y enfermedades en cucurbitáceas | F87: Agrosistemas Sustentables | G87: VEGA CANDIA, BARBARA CHANTAL | H87: INIA | I87: 487 | J87: Adjudicado | K87: Si | L87: Si | M87: Aprobado
A88: 9 | B88: 44743 | C88: FONDECYT Regular | D88: 16-Rayentué | E88: Caracterización e identificación de los factores genéticos de la resistencia al cáncer bacterial en cerezos (Prunus avium L.) presentes en cv Santina | F88: Producción Vegetal | G88: SAGREDO DIAZ, BORIS | H88: INIA | I88: 464 | J88: Adjudicado | K88: Si | L88: Si
A89: 10 | B89: 44652 | C89: ANID Idea I&D | D89: 16-Rayentué | E89: Herramientas para determinar las características de la población del agente causal del cáncer bacterial en cerezos: Generando información clave para el desarrollo de estrategias sustentables de control | F89: Producción Vegetal | G89: SAGREDO DIAZ, BORIS | H89: INIA | I89: 418 | J89: Adjudicado | K89: Si | L89: Si
A90: 11 | B90: 44599 | C90: FONDECYT Iniciación 2024 | D90: 16-Rayentué | E90: Effect of drought on the plasticity of physiological and agronomic traits in Lactuca sativa L. cultivars, under the context of climate change of southern Chile | F90: Producción Vegetal | G90: ESTRADA BRAVO, FELIX RODOLFO | H90: INIA | I90: 411 | J90: No Adjudicado | K90: Si | L90: No
A91: 12 | B91: 44496 | C91: FIA Asignacion Directa | D91: 16-Rayentue | E91: Programa de innovación en el uso eficiente del recurso hídrico para la pequeña agricultura de la región de O'Higgins | F91: Agrosistemas Sustentables | G91: FELMER ECHEVERRIA, SOFIA | H91: INIA | I91: 400 | J91: Adjudicado | K91: SI | L91: Si
A92: 13 | B92: 44377 | C92: Fondecyt Regular 2022 | D92: 16-Rayentue | E92: FLOWERING IN A WARM CLIMATE: EFFECT(S) OF HIGH TEMPERATURE ON FLORAL BUD DEVELOPMENT IN SWEET CHERRY TREES (Prunus avium L.) | F92: Producción Vegetal | G92: SAGREDO DIAZ, BORIS | H92: CEAF | I92: 249 | J92: No Adjudicado | K92: SI | L92: No
A93: 14 | B93: 44377 | C93: Fondecyt Regular 2022 | D93: 16-Rayentue | E93: Identification of QTLs and candidate genes associated with differential susceptibilty/resistance to bacterial canker in segragating progenies of sweet cherry (Prunus avium L.). | F93: Producción Vegetal | G93: SAGREDO DIAZ, BORIS | H93: INIA | I93: 246 | J93: No Adjudicado | K93: SI | L93: No
A94: 15 | B94: 44277 | C94: Proyectos de Innovación Región de O'Higgins 2021 | D94: 16-Rayentue | E94: Manejo sustentable de agua, suelos y cultivos, para enfrentar la escasez hídrica, erosión, y consecuencias de los incendios forestales, por efecto del cambio climático, en las comunas de Pumanque, Paredones, Litueche y La Estrella. Región de O`Higgins | F94: Agrosistemas Sustentables | G94: CARRASCO JIMENEZ JORGE | H94: INIA | I94: 211 | J94: No Postulado | K94: NO | L94: NO APLICA | M94: No alcanzo a presentar el proyecto
A95: 16 | B95: 44277 | C95: Proyectos de Innovación Región de O'Higgins 2021 | D95: 16-Rayentue | E95: Desarrollo de una aplicación online para la optimización del uso de plaguicidas en cítricos como adaptación al cambio climático para la región de O’Higgins | F95: Producción Vegetal | G95: ABARCA REYES, LUIS PATRICIO | H95: INIA | I95: 209 | J95: No Adjudicado | K95: SI | L95: No
A96: 17 | B96: 44256 | C96: Concurso IDeA I+D 2021 | D96: 16-Rayentue, 20-Quilamapu | E96: Celdas Solares Flexibles a base de Silica Biogénica y Grafeno (FlexSiGraf) | F96: Producción Vegetal | G96: SAGREDO DIAZ, BORIS | H96: UA - Universidad Autónoma de Chile; UDEC - Universidad de Concepción | I96: 197 | J96: No Adjudicado | K96: SI | L96: N
A97: 1 | B97: 44251 | C97: Concurso IDeA I+D 2021 | D97: 16-Rayentue, 20-Quilamapu | E97: Desarrollo y validación de una herramienta molecular para monitorear las poblaciones epifitas de Pseudomonas syringae pv syringae para optimizar el control del cáncer bacterial en cerezos | F97: Producción Vegetal | G97: SAGREDO DIAZ, BORIS | H97: INIA | I97: 190 | J97: Perfil no Seleccionado | K97: NO | L97: RECHAZADO
A98: 2 | B98: 44245 | C98: IV Concurso Nacional de Financiamiento Basal para Centros Científicos y Tecnológicos | D98: 16-Rayentue | E98: Center on Smart Agriculture for a One Health Future | F98: Producción Vegetal | G98: SAGREDO DIAZ, BORIS | H98: UOH - Universidad de O'Higgins | I98: 184 | J98: Perfil no Seleccionado | K98: NO | L98: RECHAZADO
A99: 3 | B99: 44111 | C99: I Concurso Nodos para la Aceleración de Impacto Territorial de la CTCI año 2020 | D99: 16-Rayentue, 20-Quilamapu | E99: Economía Circular y Sostenibilidad en los Procesos Industriales de la Macrozona Centro-Sur: Aseguramiento Agroalimentario | F99: Producción Vegetal | G99: SAGREDO DIAZ, BORIS | H99: U. Autonoma | I99: 127 | J99: No Adjudicado | K99: SI | L99: No
A100: 4 | B100: 44083 | C100: Convocatoria Nacional de Proyectos 2020-2021 FIA | D100: 16-Rayentue, 20-Quilamapu | E100: Potenciamiento del cultivo de Quínoa como una alternativa productiva sustentable en la Región del Maule y valoración de la calidad nutricional de los granos | F100: Producción Vegetal | G100: ALFARO JARA, CHRISTIAN EUGENIO | H100: U Talca | I100: 126 | J100: Rechazado | K100: NO | L100: NO APLICA
A101: 5 | B101: 44083 | C101: Convocatoria Nacional de Proyectos 2020-2021 FIA | D101: 16-Rayentue | E101: Plataforma virtual para el ajuste de parámetros operativos en pulverizadores agrícolas para la aplicación eficiente de plaguicidas en cítricos | F101: Producción Vegetal | G101: ABARCA REYES, LUIS PATRICIO | H101: INIA | I101: 123 | J101: Perfil no Seleccionado | K101: NO | L101: NO APLICA
A102: 6 | B102: 44083 | C102: Convocatoria Nacional de Proyectos 2020-2021 FIA | D102: 16-Rayentue | E102: Elaboración y utilización de pellet a partir de lana ovina de descarte, para optimizar los recursos hídricos y mitigar el efecto del cambio climático. | F102: Agrosistemas Sustentables | G102: AGUIRRE AGUILERA, CRISTIAN | H102: INIA | I102: 117 | J102: Perfil no Seleccionado | K102: NO | L102: NO APLICA
A103: 7 | B103: 44074 | C103: Fondecyt de Postdoctorado 2021 | D103: 16-Rayentue | E103: Determination of root traits of durum wheat (Triticum turgidum L. spp. Durum) released from 1915 to 2015 to improve wheat grain yield in the Mediterranean dry land environments. | F103: Producción Vegetal | G103: ALFARO JARA, CHRISTIAN EUGENIO | H103: INIA | I103: 67 | J103: No Adjudicado | K103: SI | L103: No
B104: 44083 | C104: Convocatoria Nacional de Proyectos 2020-2021 FIA | D104: 16-Rayentue | E104: Desarrollo y validación de un sistema automatizado de humidificación de alta presión como una herramienta multipropósito para el cultivo del cerezo bajo macrotúneles | F104: Producción Vegetal | G104: OTAROLA ALIAGA, JAIME IGNACIO | H104: INIA | I104: 64 | J104: No Adjudicado | K104: SI | L104: No | M104: Paso Admisibilidad pero no paso a 2° etapa
...

Sheet Pys Post.
D3: PROYECTOS POSTULADOS RAYENTUÉ
C8: Añode adjudicación | D8: Año Postulación2 | E8: Fuente Financiamiento | F8: Concurso o Linea | G8: CRI | H8: Titulo Proyecto | I8: Programas Nacionales | J8: Investigador/a Encargado/a | K8: Ejecutor Principal | L8: Estado | M8: ID- PERFIL | N8: Fecha de Postulación | O8: Monto solicitado | P8: Asociado Pecuniario | Q8: Asociado No Pecuniario | R8: Inia Pecuniario | S8: Inia No Pecuniario | T8: Costo Total del Proyecto | U8: Rendible a la FF | V8: Libre disposición (overhead) | W8: Duración (meses) | X8: Fecha de Aprobación | Y8: Condiciones de aprobación | Z8: Fecha de Rechazo | AA8: Motivos rechazo | AB8: Fuente de Información (Acta resolución) | AC8: Codigo Proyecto Fuente financ. | AD8: Observaciones | AE8: Monto adjudicado | AF8: Monto contrapartida | AG8: Monto aporte INIA | AH8: Monto capturado po INIA | AI8: Costo Total del proyecto4
C9: FECHA ACTUALIZACIÓN | F9: 45790
C10: RESPONSABLE | F10: Christian Núñez Berrios
O11: Ficha financiera
P12: Monto contrapartida (asociados) | R12: Monto aporte INIA | U12: Monto capturado por INIA (Gastos de Administración) | AE12: Modificaciones al presupuesto solicitado
C13: Añode adjudicación | D13: Año Postulación2 | E13: Fuente Financiamiento | F13: Concurso o Linea | G13: CRI | H13: Titulo Proyecto | I13: Programas Nacionales | J13: Investigador/a Encargado/a | K13: Ejecutor Principal | L13: Estado | M13: ID- PERFIL | N13: Fecha de Postulación | O13: Monto solicitado | P13: Asociado Pecuniario | Q13: Asociado No Pecuniario | R13: Inia Pecuniario | S13: Inia No Pecuniario | T13: Costo Total del Proyecto | U13: Rendible a la FF | V13: Libre disposición (overhead) | W13: Duración (meses) | X13: Fecha de Aprobación | Y13: Condiciones de aprobación | Z13: Fecha de Rechazo | AA13: Motivos rechazo | AB13: Fuente de Información (Acta resolución) | AC13: Codigo Proyecto Fuente financ. | AD13: Observaciones | AE13: Monto adjudicado | AF13: Monto contrapartida | AG13: Monto aporte INIA | AH13: Monto capturado po INIA | AI13: Costo Total del proyecto4
D14: =+Tabla2[[#This Row],[Fecha de Postulación]] -> 44414 | E14: Contratos Privados Internacionales | F14: FONTAGRO | G14: ='Perfiles '!D57 -> 16-Rayentué | H14: Agtechmetro | I14: Agrosistemas Sustentables | J14: FELMER ECHEVERRIA, SOFIA | K14: U. AUSTRAL | L14: RECHAZADO | M14: Sin Información | N14: 44414 | O14: No tengo la info | P14: 0 | Q14: 0 | R14: 0 | S14: 0 | T14: =SUM(O14:S14) -> 0 | U14: No tengo la info | V14: No tengo la info | W14: No tengo la info | X14: RECHAZADO | Y14: N/A | Z14: 44505 | AA14: Puntuación baja 62,67/100 y requería como minimo 75/100 | AB14: Carta FTG/6935 de fecha 5 de noviembre de 2021 | AC14: 584
C15: 2019 | D15: =+Tabla2[[#This Row],[Fecha de Postulación]] -> 43776 | E15: FONDEQUIP | F15: X Concurso de Equipamiento Científico y Tecnológico-FONDEQUIP, Región de O’Higgins, año 2019 | G15: 16-Rayentue, 20-Quilamapu, 13-La Cruz | H15: Desarrollo de una plataforma de análisis de fragmentos y secuencias de ADN para fortalecer el desarrollo científico y tecnológico de la Región de O'Higgins | I15: Producción Vegetal | J15: SAGREDO DIAZ, BORIS | K15: INIA | L15: ADJUDICADO | M15: Sin Información | N15: 43776 | O15: 90000000 | P15: 3700000 | Q15: 0 | R15: 4500000 | S15: 22427400 | T15: =SUM(O15:S15) -> 120627400 | U15: 0 | V15: 0 | W15: 18 | X15: 44174 | Z15: N/A | AA15: N/A | AB15: Res. Exento N°12525/2020 | AC15: EQUR190005 | AE15: 90000000 | AF15: 1500000 | AG15: 26927400 | AH15: 0 | AI15: =AE15+AF15+AG15 -> 118427400
C16: 2019 | D16: =+Tabla2[[#This Row],[Fecha de Postulación]] -> 43776 | E16: CONICYT | F16: Anillos de Investigación en Ciencia Y tecnología para la Región de O´Higgins 2019 | G16: 16-Rayentué | H16: Deep insight in the cherry plant defense responses to bacterial canker disease in a scenario of water restriction | I16: Producción Vegetal | J16: SAGREDO DIAZ, BORIS | K16: UOH | L16: ADJUDICADO | M16: Sin Información | N16: 43776 | O16: 112500000 | P16: 0 | Q16: 0 | R16: 0 | S16: 57780300 | T16: =SUM(O16:S16) -> 170280300 | U16: 0 | V16: 0 | W16: 36 | X16: 44096 | Z16: N/A | AA16: N/A | AB16: Res. Exenta N°10451/2020 | AE16: 32697647 | AF16: 0 | AG16: 57780349 | AH16: 0 | AI16: =AE16+AF16+AG16 -> 90477996
D17: =+Tabla2[[#This Row],[Fecha de Postulación]] -> 43755 | E17: FONDEF | F17: VIII Concurso de Investigación Tecnológica 2019-IDeA | G17: 16-Rayentue | H17: Validación de la tecnología de nanoburbujas en distintos niveles de la cadena de producción de fruta fresca | I17: Producción Vegetal | J17: OTAROLA ALIAGA, JAIME IGNACIO | K17: INIA | L17: RECHAZADO | M17: Sin Información | N17: 43755 | O17: 188241000 | P17: 60000000 | Q17: 0 | R17: 0 | S17: 39556000 | T17: =SUM(O17:S17) -> 287797000 | U17: 21850000 | V17: 0 | W17: 24 | X17: =L17 -> RECHAZADO | Y17: N/A | Z17: 43847 | AA17: Nota 2,6 | AB17: Informe de Evaluación recibido por mail
C18: 2019 | D18: =+Tabla2[[#This Row],[Fecha de Postulación]] -> 43732 | E18: FONDECYT | F18: FONDECYT DE POSTDOCTORADO 2020 | G18: 16-Rayentue, 15-Hidango, 20-Quilamapu, 14-Los Tilos | H18: DETERMINACIÓN DE LAS BASES FISIOLÓGICAS DE LA ADAPTACIÓN DE GENOTIPOS DE TRIGO CANDEAL DE INIA A CONDICIONES DE SEQUÍA EN EL SECANO MEDITERRÁNEO DE CHILE | I18: Producción Vegetal | J18: ALFARO JARA, CHRISTIAN EUGENIO | K18: INIA | L18: ADJUDICADO | M18: Sin Información | N18: 43732 | O18: 0 | P18: 0 | Q18: 0 | R18: 0 | S18: 13262000 | T18: =SUM(O18:S18) -> 13262000 | U18: 0 | V18: 0 | W18: 36 | X18: 43902 | Z18: N/A | AA18: N/A | AB18: Carta N°018/FONDECYT/UGC/189 | AC18: 3200742 | AE18: 0 | AF18: 0 | AG18: 13262000 | AH18: 0 | AI18: =AE18+AF18+AG18 -> 13262000
D19: =+Tabla2[[#This Row],[Fecha de Postulación]] -> 43707 | E19: INNOVA-CORFO | F19: Bienes Públicos 2019- Temática "Adaptación al Cambio Climático" | G19: 16-RAYENTUE | H19: Adaptación al manejo agronómico del cultivo de cerezo desarrollado bajo cubiertas plásticas | I19: Producción Vegetal | J19: OTAROLA ALIAGA, JAIME IGNACIO | K19: INIA | L19: RECHAZADO | M19: Sin Información | N19: 43707 | O19: 100202000 | P19: 15990000 | Q19: 0 | R19: 5100000 | S19: 17755000 | T19: =SUM(O19:S19) -> 139047000 | U19: =O19+P19+R19 -> 121292000 | V19: 0 | W19: 36 | X19: =L19 -> RECHAZADO | Y19: N/A | Z19: 43741 | AA19: No es pertinente | AB19: Oficio N°02804 | AC19: 19BP-117383 | AD19: numeral 12.2 de las bases, se concluyó que su proyecto no cumplió con todos los requisitos de dicho análisis y, por lo tanto, es no pertinente
D20: =+Tabla2[[#This Row],[Fecha de Postulación]] -> 43682 | E20: FNDR O'Higgins | F20: Fondos 2020 | G20: 16-Rayentue | H20: Diseño Ampliación edificio INIA | I20: No aplica | J20: BARTEL CLAUDIA | K20: INIA | L20: OT | M20: Sin Información | N20: 43682 | O20: 12285000 | P20: 0 | Q20: 0 | R20: 0 | S20: 0 | T20: =SUM(O20:S20) -> 12285000 | W20: 10 | X20: NO SE SIGUIO CON LOS PROCESOS MOP, CORES, INTENDENTE | Y20: RS | AC20: Código BIP : 40013817 | AI20: =AE20+AF20+AG20 -> 0
D21: =+Tabla2[[#This Row],[Fecha de Postulación]] -> 43620 | E21: CONICYT | F21: Concurso Regular Fondecyt 2020 | G21: 14-LOS TILOS, 16-RAYENTUE, 10-LA PLATINA, 05-INTIHUASI | H21: Disentangling the epigenetic influence on fruit development and ripening in three stone fruits Prunus species | I21: Producción Vegetal | J21: DONOSO CONTRERAS JOSE MANUEL | K21: UCH | L21: Rechazado | M21: Sin Información | N21: 43620 | O21: 3664000 | P21: 0 | Q21: 0 | R21: 0 | S21: 9650000 | T21: =SUM(O21:S21) -> 13314000 | U21: 0 | V21: 0 | W21: 48 | X21: 21-12-2019 | Z21: N/A | AA21: N/A | AB21: Respuesta enviada a UCH | AE21: 3664000 | AF21: 0 | AG21: 9650000 | AH21: 0 | AI21: =AE21+AF21+AG21 -> 13314000
D22: =+Tabla2[[#This Row],[Fecha de Postulación]] -> 43616 | E22: CONICYT | F22: PCI ECOS CONICYT Concurso de proyectos de intercambio Chile Francia 2019 | G22: 14-LOS TILOS, 10-LA PLATINA, 16-RAYENTUE | H22: Collaborative counter season research efforts between France and Chile analysis of traits affected by climate change in sweet cherry in order to create new varieties adapted to future environmental conditions | I22: Producción Vegetal | J22: DONOSO CONTRERAS JOSE MANUEL | K22: INIA | L22: RECHAZADO | M22: Sin Información | N22: 43616 | O22: 12900000 | P22: 0 | Q22: 0 | R22: 0 | S22: 250000 | T22: =SUM(O22:S22) -> 13150000 | W22: 36 | X22: RECHAZADO | Y22: N/A | Z22: 43936
D23: =+Tabla2[[#This Row],[Fecha de Postulación]] -> 43396 | E23: CONICYT | F23: Concurso Postdoctorado 2019 | G23: 16-RAYENTUE | H23: INTERACCIÓN G X E DE CARACTERES MORFO-FISIOLÓGICOS DE ADAPTACIÓN A CONDICIONES DE SEQUÍA Y SU EFECTO EN LA DETERMINACIÓN DEL RENDIMIENTO EN TRIGO CANDEAL. Marcela Opazo - opazo.marcela@gmail.com | I23: Producción Vegetal | J23: ALFARO JARA, CHRISTIAN EUGENIO | K23: INIA | L23: RECHAZADO | M23: Sin Información | N23: 43396 | O23: 0 | P23: 0 | Q23: 17000000 | R23: 17000000 | S23: 0 | T23: =SUM(O23:S23) -> 34000000 | W23: 36 | X23: RECHAZADO | Y23: CARTA DIRIGIDA A MARCELA OPAZO, INVESTIGADORA PPAL. | Z23: 43535 | AA23: QUEDARON ABAJO DEL PUNTAJE DE CORTE
D24: =+Tabla2[[#This Row],[Fecha de Postulación]] -> 43347 | E24: FONDECYT | F24: Concurso Regular Fondecyt 2019 | G24: 16-RAYENTUE | H24: HYDRAULIC MECHANISMS AND CARBON METABOLISM IN THE ADAPTATION OF WHEAT TO CONDITIONS OF CLIMATE CHANGE IN SEVERE DROUGHT MEDITERRANEAN ENVIRONMENTS/ MECANISMOS HIDRAULICOS Y DE METABOLISMO DEL CARBONO EN LA ADAPTACION DEL CULTIVO DE TRIGO A CONDICIONES DE CAMBIO CLIMÁTICO EN AMBIENTES DE SEQUIA SEVERA DE TIPO MEDITERRANEO | I24: Producción Vegetal | J24: ALFARO JARA, CHRISTIAN EUGENIO | K24: U. Chile | L24: RECHAZADO | M24: Sin Información | N24: 43347 | O24: 25400000 | P24: 0 | Q24: 10000000 | R24: 35400000 | T24: =SUM(O24:S24) -> 70800000 | W24: 48 | X24: RECHAZADO | Y24: carta N°018/Fondecyt/22 | Z24: 43543 | AA24: puntaje
C25: 2018 | D25: =+Tabla2[[#This Row],[Fecha de Postulación]] -> 43291 | E25: FNDR Antofagasta | F25: Fondos 2019 | G25: 16-Rayentué | H25: Tranferencia Control Mostaza negra -El Loa | I25: Agrosistemas Sustentables | J25: VEGA CANDIA, BARBARA CHANTAL | K25: INIA | L25: ADJUDICADO | M25: Sin Información | N25: 43291 | O25: 1028356000 | P25: 0 | Q25: 29540000 | R25: 0 | S25: 70754000 | T25: =SUM(O25:S25) -> 1128650000 | U25: 48969000 | W25: 36 | X25: 17-09-2019 | Z25: N/A | AA25: N/A | AB25: Acuerdo CORE 15352-19 | AC25: Cod. BIP. 40002794-0 | AE25: 1028356000 | AF25: 29540000 | AG25: 70754000 | AH25: 0 | AI25: =AE25+AF25+AG25 -> 1128650000
D26: 46087 | E26: Corporación Nacional Forestal | F26: XVII Concurso Fondo de Investigación del Bosque Nativo-CONAF 2026 | G26: 16-RAYENTUE | H26: Restauración de bosques fragmentados del secano costero de la Región de O’Higgins mediante el uso de especies nodrizas leñosas y cactáceas nativas | I26: Programa Nacional de Agrosistemas Sustentables | J26: CACERES CELEDON, EMILIO JOSE | K26: INIA | L26: En concurso | M26: 1617 | N26: 46087 | O26: 75000000 | P26: 0 | Q26: 2692825 | R26: 0 | S26: 64944210 | T26: =SUM(O26:S26) -> 142637035
D27: 46100 | E27: ANID | F27: Concurso de Investigación Tecnológica IDeA 2026 | G27: 16-RAYENTUE | H27: Hacia un control mas sustentable del cáncer bacterial en cerezos: reducción del uso de cobre y pérdidas productivas mediante herramientas biotecnológicas y monitoreo molecular predictivo | I27: Programa Nacional de Producción Vegetal | J27: SAGREDO DIAZ, BORIS | K27: INIA | L27: En concurso | M27: 1615 | N27: 46100 | O27: 237000000 | P27: 23700000 | Q27: 47400000 | R27: 100518777 | S27: 0 | T27: =SUM(O27:S27) -> 408618777
D28: 45944 | E28: INNOVA-CORFO | F28: Viraliza Eventos 2025 | G28: Rayentué | H28: Viraliza Agro Tech O’Higgins (Viraliza Eventos 2025) | I28: Programa Nacional de Agrosistemas Sustentables | J28: AGUIRRE AGUILERA, CRISTIAN | K28: UOH - Universidad de O'Higgins | L28: Adjudicado | M28: 1553 | N28: 45951 | O28: 0 | P28: 0 | Q28: 0 | R28: 0 | S28: 3574816 | T28: =SUM(O28:S28) -> 3574816 | U28: 0 | V28: 0 | W28: 8
D29: 45901 | E29: FIA | F29: Consultorías Regionales para la Innovación 2025 | G29: Rayentué | H29: Gestión eficiente del agua de riego de Convento Viejo 2: diagnóstico de suelos, riego y cultivos en las comunas de Lolol, Pumanque y Marchigue | I29: Programa Nacional de Agrosistemas Sustentables | J29: CACERES CELEDON, EMILIO JOSE | K29: INIA | L29: Adjudicado | M29: 1523 | N29: 45937 | O29: 10000000 | P29: 500000 | Q29: 0 | R29: 0 | S29: 25763869 | T29: =SUM(O29:S29) -> 36263869 | V29: 0 | W29: 9
D30: 45901 | E30: FIA | F30: Giras nacionales de innovación para Mujeres Agroinnovadoras 2025 | G30: Rayentué | H30: Raíces femeninas: Gira agroecológica de mujeres transformadoras | I30: Programa Nacional de Agrosistemas Sustentables | J30: VEGA CANDIA, BARBARA CHANTAL | K30: INIA | L30: No adjudicado | M30: 1522 | N30: 45937 | O30: 14629621 | P30: 0 | Q30: 0 | R30: 250000 | S30: 1416288 | T30: =SUM(O30:S30) -> 16295909 | V30: 0 | W30: 1
D31: 45886 | E31: ANID | F31: Startup Ciencia 2026 | G31: Rayentué | H31: Optiriego Plus: Aceleramiento del desarrollo tecnológico y comercial del sensor Optiriego para optimizar el manejo del riego en uva vinífera (Startup Ciencia 2026) | I31: Programa Nacional de Producción Vegetal | J31: MARTINEZ CASTILLO, JUAN PABLO | K31: YUMMY TECH LIMITADA | L31: Postulado | M31: 1472 | N31: 45910 | O31: 20971432 | P31: 16877582 | Q31: 30000000 | R31: 0 | S31: 30299906 | T31: =SUM(O31:S31) -> 98148920 | U31: 0 | V31: 0 | W31: 12
D32: 45874 | E32: ANID | F32: IDeA I+D 2026 | G32: Rayentué | H32: Desarrollo y validación de modelos de predicción genómica en cerezo para una selección anticipada y precisa de nuevas variedades | I32: Programa Nacional de Producción Vegetal | J32: DONOSO CONTRERAS, JOSE MANUEL | K32: UCHILE - Universidad de Chile | L32: En concurso | M32: 1467 | N32: 45930 | O32: 46964800 | P32: 0 | Q32: 68859600 | R32: 0 | S32: 38923792 | T32: =SUM(O32:S32) -> 154748192 | V32: 6831000 | W32: 24
D33: 45860 | E33: FIA | F33: Convocatoria Nacional Proyectos de Innovación para el Agro 2025-2026 FIA-Propuesta completa | G33: Rayentué | H33: Herramienta digital para la inspección de pulverizadores hidroneumáticos utilizados en huertos frutales | I33: Programa Nacional de Producción Vegetal | J33: ABARCA REYES, LUIS PATRICIO | K33: INIA | L33: No adjudicado | M33: 1444 | N33: 45860 | O33: 149890000 | P33: 1000000 | Q33: 840000 | R33: 300000 | S33: 59106880 | T33: =SUM(O33:S33) -> 211136880 | V33: 10440000
D34: 45860 | E34: FIA | F34: Convocatoria Nacional Proyectos de Innovación para el Agro 2025-2026 FIA-Propuesta completa | G34: Rayentué | H34: Gestión sostenible del rendimiento y calidad del trigo en el secano interior de sequía severa en la Región de O'Higgins, aumentando la EUA y EUN. | I34: Programa Nacional de Producción Vegetal | J34: RUBILAR TORRES, FELIPE ANDRES | K34: UCHILE - Universidad de Chile | L34: No adjudicado | M34: 1412 | N34: 45860 | O34: 50389000 | P34: 0 | Q34: 0 | R34: 0 | S34: 26854376 | T34: =SUM(O34:S34) -> 77243376 | V34: 0
D35: 45860 | E35: FIA | F35: Convocatoria Nacional Proyectos de Innovación para el Agro 2025-2026 FIA-Propuesta completa | G35: Rayentué | H35: Optimización del manejo y diseño de invernaderos hortícolas mediante una plataforma de monitoreo ambiental en la Región de O’Higgins | I35: Programa Nacional de Producción Vegetal | J35: MARTINEZ CASTILLO, JUAN PABLO | K35: INIA | L35: No adjudicado | M35: 1395 | N35: 45860 | O35: 119473199 | P35: 7000000 | Q35: 25973914 | R35: 0 | S35: 36416048 | T35: =SUM(O35:S35) -> 188863161 | V35: 8328000
D36: 45860 | E36: FIA | F36: Convocatoria Nacional Proyectos de Innovación para el Agro 2025-2026 FIA-Propuesta completa | G36: Rayentué | H36: Estrategias para mitigar el daño por piel de lagarto en cerezas de exportación | I36: Programa Nacional de Producción Vegetal | J36: DONOSO CONTRERAS, JOSE MANUEL | K36: INIA | L36: Adjudicado | M36: 1388 | N36: 45860 | O36: 149624480 | P36: 6000000 | Q36: 13800000 | R36: 0 | S36: 50361000 | T36: =SUM(O36:S36) -> 219785480 | V36: 9435020
D37: 45860 | E37: FIA | F37: Convocatoria Nacional Proyectos de Innovación para el Agro 2025-2026 FIA-Propuesta completa | G37: Rayentué | H37: Validación de un modelo de alerta preventiva contra los principales hongos de madera que afectan al cultivo del cerezo para mantener los estándares de calidad y competitividad en el mercado | I37: Programa Nacional de Producción Vegetal | J37: OTAROLA ALIAGA, JAIME IGNACIO | K37: INIA | L37: Adjudicado | M37: 1387 | N37: 45860 | O37: 149784006 | P37: 8000000 | Q37: 0 | R37: 1000000 | S37: 77389479 | T37: =SUM(O37:S37) -> 236173485 | V37: 10400000
D38: 45832 | E38: FONDECYT | F38: Fondecyt Regular 2026 | G38: Rayentué | H38: Disentangling the epigenetic influence on differentiation of fruit development between early and late varieties in sweet cherry (Prunus avium) | I38: Programa Nacional de Producción Vegetal | J38: DONOSO CONTRERAS, JOSE MANUEL | K38: UCHILE - Universidad de Chile | L38: No adjudicado | M38: 1363 | N38: 45832 | O38: 10730000 | P38: 0 | Q38: 0 | R38: 0 | S38: 7360706 | T38: =SUM(O38:S38) -> 18090706 | U38: 0
D39: 45832 | E39: FONDECYT | F39: Fondecyt Regular 2026 | G39: Rayentué | H39: Improving salinity tolerance in ‘Old Limachino Tomato’ through grafting onto two clonal rootstocks derived from reciprocal interspecific crosses between cultivated and wild tomato genotypes | I39: Programa Nacional de Producción Vegetal | J39: MARTINEZ CASTILLO, JUAN PABLO | K39: INIA | L39: Adjudicado | M39: 1362 | N39: 45832 | O39: 271644000 | P39: 0 | Q39: 0 | R39: 0 | S39: 148519718 | T39: =SUM(O39:S39) -> 420163718 | U39: 45274000 | V39: 0
D40: =+Tabla2[[#This Row],[Fecha de Postulación]] -> 45777 | E40: FONDECYT | F40: Fondecyt de Iniciación en Investigación 2026 | G40: 16-Rayentué | H40: Identification of stable and heritable physiological traits for the selection of drought-tolerant quinoa (Chenopodium quinoa Willd.) genotypes under drought environments | I40: Producción Vegetal | J40: ESTRADA BRAVO, FELIX RODOLFO | K40: INIA | L40: No adjudicado | M40: 1303 | N40: 45777 | O40: 104400000 | P40: 0 | Q40: 0 | R40: 0 | S40: 63067518 | T40: =SUM(O40:S40) -> 167467518 | U40: 14400000 | V40: 0 | W40: 36
D41: =+Tabla2[[#This Row],[Fecha de Postulación]] -> 45736 | E41: FONDEF | F41: Concurso de Investigación Tecnológica IDeA 2025 | G41: 16-Rayentué | H41: GENERANDO INFORMACIÓN CLAVE PARA EL DESARROLLO DE ESTRATEGIAS SUSTENTABLES DE CONTROL DEL CANCER BACTERIAL EN CEREZOS: BASADOS EN LAS CARACTERÍSTICAS DE LA POBLACIÓN DEL AGENTE CAUSAL | I41: Producción Vegetal | J41: SAGREDO DIAZ, BORIS | K41: INIA | L41: No adjudicado | M41: 1267 | N41: 45736 | O41: 237000000 | P41: 0 | Q41: 71100001 | R41: 0 | S41: 111029264 | T41: =SUM(O41:S41) -> 419129265 | U41: 28000000 | V41: 0 | W41: 24
D42: 45622 | E42: FIA | F42: Convocatoria Nacional Proyectos de Innovación para el agro con Énfasis Regional 2024-2025 FIA | G42: 16-Rayentué | H42: Desarrollo de estrategias de riego deficitario controlado en diferentes variedades de cerezos y zonas agroclimáticas de Chile con baja disponibilidad hídrica. | I42: Programa Nacional de Agrosistemas Sustentables | J42: CACERES CELEDON, EMILIO JOSE | K42: INIA | L42: No adjudicado | M42: 1213 | N42: 45622 | O42: 150000000 | P42: 5000000 | Q42: 5000000 | R42: 0 | S42: 83701088 | T42: =SUM(O42:S42) -> 243701088 | V42: 5 | W42: 36
D43: 45622 | E43: FIA | F43: Convocatoria Nacional Proyectos de Innovación para el agro con Énfasis Regional 2024-2025 FIA | G43: 16-Rayentué | H43: Empaquetamiento técnico y comercial de la primera variedad de cereza chilena para un mercado de alta exigencia en calidad | I43: Producción Vegetal | J43: OTAROLA ALIAGA, JAIME IGNACIO | K43: INIA | L43: Adjudicado | M43: 1209 | N43: 45622 | O43: 119808000 | P43: 2000000 | Q43: 0 | R43: 0 | S43: 52719999 | T43: =SUM(O43:S43) -> 174527999 | U43: 8300000 | W43: 36
D44: 45626 | E44: FRPD | F44: Fondo Regional para la Productividad y el Desarrollo (FRPD)- Región de O'Higgins 2024 | G44: 16-Rayentué | H44: Desarrollo de la agricultura urbana y periurbana como alternativa de desarrollo sostenible para la producción de alimentos en la Región de O`Higgins. | I44: Programa Nacional de Agrosistemas Sustentables | J44: RUBILAR TORRES, FELIPE ANDRES | K44: INIA | L44: Adjudicado | M44: 1165 | N44: 45626 | O44: 203909000 | P44: 10200000 | Q44: 1000000 | R44: 0 | S44: 9193390 | T44: =SUM(O44:S44) -> 224302390 | U44: 10000000 | W44: 36
D45: 45626 | E45: FRPD | F45: Fondo Regional para la Productividad y el Desarrollo (FRPD)- Región de O'Higgins 2024 | G45: 16-Rayentué | H45: Transferencia de un paquete tecnológico para el control de ataques de depredadores en ovinos del secano costero de O’Higgins. | I45: Programa Nacional de Producción Animal | J45: QUEZADA JARA, MARCELO | K45: INIA | L45: Adjudicado | M45: 1163 | N45: 45626 | O45: 280000000 | P45: 15000000 | Q45: 0 | R45: 0 | S45: 21085437 | T45: =SUM(O45:S45) -> 316085437 | U45: 13720000 | W45: 36
D46: 45576 | E46: FRPD | F46: Fondo Regional para la Productividad y el Desarrollo (FRPD)- Región de O'Higgins 2024 | G46: 16-Rayentué | H46: Transferencia del diagnóstico y manejo integrado de enfermedades del almendro: estrategias innovadoras para aumentar la competitividad del cultivo en la región de ohiggins | I46: Programa Nacional de Agrosistemas Sustentables | J46: RIQUELME TOLEDO, DANAE | K46: INIA | L46: Adjudicado | M46: 1162 | N46: 45626 | O46: 280000000 | P46: 14000000 | Q46: 0 | R46: 0 | S46: 138674506 | T46: =SUM(O46:S46) -> 432674506 | U46: 14000000 | V46: 0 | W46: 36
D47: =+Tabla2[[#This Row],[Fecha de Postulación]] -> 45626 | E47: FRPD | F47: Fondo Regional para la Productividad y el Desarrollo (FRPD)- Región de O'Higgins 2024 | G47: 16-Rayentué | H47: Biofábricas en la región de O´Higgins, una alternativa a la producción de agroinsumos con visión agroecológica | I47: Programa Nacional de Agrosistemas Sustentables | J47: VEGA CANDIA, BARBARA CHANTAL | K47: INIA | L47: No adjudicado | M47: 1158 | N47: 45626 | O47: 256543408 | P47: 16500000 | S47: 24853209 | T47: =SUM(O47:S47) -> 297896617 | U47: 12486286 | W47: 36
A48: 2 | D48: 45576 | E48: FRPD | F48: Fondo Regional para la Productividad y el Desarrollo (FRPD)- Región de O'Higgins 2024 | G48: 16-Rayentué | H48: Sistema de detección y alerta en tiempo real para el control preventivo y oportuno de las principales enfermedades de madera que afectan a los frutales de carozo | I48: Programa Nacional de Agrosistemas Sustentables | J48: ALTIMIRA PASSALACQUA, FABIOLA | K48: INIA | L48: Adjudicado | M48: 1153 | N48: 45626 | O48: 280000000 | P48: 14000000 | Q48: 6750000 | R48: 0 | S48: 71816598 | T48: =SUM(O48:S48) -> 372566598 | U48: 14000000 | V48: 0 | W48: 36
A49: 3 | D49: 45512 | E49: CORFO | F49: Red de Fomento Sostenible-1º Convocatoria 2024-Sector Agricultura | G49: 16-Rayentué | H49: “RedFrutiT: Red de innovación tecnológica para una fruticultura sustentable y resiliente en Chile” (Red de Fomento Sostenible-1º Convocatoria 2024-Sector Agricultura) | I49: Producción Vegetal | J49: OTAROLA ALIAGA, JAIME IGNACIO | K49: UC DAVIS CHILE - FUNDACION UC DAVIS CHILE LIFE SCIENCES INNOVATION CENTER | L49: No adjudicado | M49: 1112 | N49: 45512 | O49: 103327093 | P49: 0 | Q49: 0 | R49: 0 | S49: 70763724 | T49: =SUM(O49:S49) -> 174090817 | U49: 5127040 | W49: 36
A50: 4 | D50: =+Tabla2[[#This Row],[Fecha de Postulación]] -> 44301 | E50: FIA | F50: ='Perfiles '!C61 -> Fondo Regional para la Productividad y el Desarrollo (FRPD)- Región de O'Higgins 2024 | G50: ='Perfiles '!D61 -> 16-Rayentué | H50: ='Perfiles '!E61 -> Biofábricas en la región de O´Higgins, una alternativa a la producción de agroinsumos con visión agroecológica | I50: Producción Vegetal | J50: ='Perfiles '!G61 -> VEGA CANDIA, BARBARA CHANTAL | K50: ='Perfiles '!H61 -> INIA | L50: No adjudicado | M50: 1112 | N50: 44301 | O50: 90000000 | P50: 7125000 | Q50: 500000 | R50: 0 | S50: 44838934 | T50: =SUM(O50:S50) -> 142463934 | U50: 4500000 | V50: 0 | W50: 36 | X50: =L50 -> No adjudicado | Y50: N/A | Z50: 44407 | AB50: listado proyectos aprobados y no aprobados de acuerdo con el numeral 2.2.3 “Adjudicación” de las Bases Técnicas y Administrativas
A51: 5 | D51: 45547 | E51: Anid | F51: IDeA I+D 2025 | G51: 16-Rayentué | H51: Desarrollo de un sistema de producción de plantas de tomate injertadas sobre portainjertos clonales originados por cruzamientos interespecíficos (S. lycopersicum x S. chilense) para mejorar la productividad y calidad de tomate fresco. | I51: Producción Vegetal | J51: MARTINEZ CASTILLO, JUAN PABLO | K51: INIA | L51: No adjudicado | M51: 1109 | N51: 45547 | O51: 227654080 | P51: 26200000 | Q51: 77874000 | R51: 0 | S51: 144158566 | T51: =SUM(O51:S51) -> 475886646 | U51: 34000000 | W51: 24
A52: es | D52: 45447 | E52: FONDECYT | F52: Fondecyt Regular 2025 | G52: 16-Rayentué | H52: Improving salt tolerance of “Old Limachino Tomato” by using two clonal rootstocks issued from interspecific reciprocal crosses between wild and cultivated tomato, with different level of salt tolerance. | I52: Producción Vegetal | J52: MARTINEZ CASTILLO, JUAN PABLO | K52: INIA | L52: No adjudicado | M52: 1046 | N52: 45500 | O52: 273055000 | P52: 0 | Q52: 0 | R52: 0 | S52: 156885440 | T52: =SUM(O52:S52) -> 429940440 | U52: 45509000 | V52: 0 | W52: 48 | X52: RECHAZADO | Y52: N/A
A53: 7 | D53: 45500 | E53: FONDECYT | F53: Fondecyt Regular 2025 | G53: 16-Rayentué | H53: Disentangling the epigenetic influence on differentiation of fruit development between early and late varieties in sweet cherry (Prunus avium) (FONDECYT REGULAR) | I53: Producción Vegetal | J53: DONOSO CONTRERAS JOSE MANUEL | K53: UCHILE - Universidad de Chile | L53: No adjudicado | M53: 1045 | N53: 45500 | O53: 4500000 | P53: 0 | Q53: 0 | R53: 0 | S53: 14095330 | T53: =SUM(O53:S53) -> 18595330 | U53: 0 | W53: 48
A54: 1 | D54: 45500 | E54: FONDECYT | F54: Fondecyt Regular 2025 | G54: 16-Rayentué | H54: Understanding the genetics related to orange peel disorder in sweet cherry (Prunus avium L.) | I54: Producción Vegetal | J54: DONOSO CONTRERAS JOSE MANUEL | K54: INIA | L54: No adjudicado | M54: 1043 | N54: 45500 | O54: 226809533 | P54: 0 | Q54: 0 | R54: 0 | S54: 108294655 | T54: =SUM(O54:S54) -> 335104188 | U54: 33966000 | W54: 48
D55: 45427 | E55: FONDECYT | F55: Fondecyt de Iniciación en Investigación 2025 | G55: 16-Rayentué | H55: A comprehensive characterization of physiological and agronomic traits for detecting keystones to select quinoa (Chenopodium quinoa Willd.) genotypes under adverse environments | I55: Producción Vegetal | J55: ESTRADA BRAVO, FELIX RODOLFO | K55: INIA | L55: No adjudicado | M55: 975 | N55: 45427 | O55: 104400000 | P55: 0 | Q55: 0 | R55: 0 | S55: 6827528 | T55: =SUM(O55:S55) -> 111227528 | U55: 14400000 | W55: 36
A56: 2 | D56: =+Tabla2[[#This Row],[Fecha de Postulación]] -> 45391 | E56: FIA | F56: Instrumentos Complementarios FIA: Giras Nacionales para la Innovación 2024 | G56: 16-Rayentué | H56: Visita a experiencias de cooperativas exitosas en la Región de Los Lagos, con productores ovinos del secano costero de la Región de O'Higgins. | I56: Programa Nacional de Producción Animal | J56: QUEZADA JARA, MARCELO | K56: INIA | L56: No adjudicado | M56: 937 | N56: 45391 | O56: 12000000 | P56: 2145335 | Q56: 0 | R56: 0 | S56: 854665 | T56: =SUM(O56:S56) -> 15000000
A57: 3 | C57: 2024 | D57: 45246 | E57: ANID | F57: Concurso Startup Ciencia 2024 (2º llamado 2023) | G57: 16-Rayentué | H57: Desarrollo de un sensor portátil (Optiriego) que optimiza el manejo de riego en tomates y uva vinífera | I57: Producción Vegetal | J57: MARTINEZ CASTILLO, JUAN PABLO | K57: YUMMY FRUIT SPA | L57: Adjudicado | M57: 879 | N57: 45246 | O57: 45574372 | P57: 0 | Q57: 0 | R57: 1500000 | S57: 44074372 | T57: =SUM(O57:S57) -> 91148744 | U57: 0 | W57: 12
A58: 4 | D58: =+Tabla2[[#This Row],[Fecha de Postulación]] -> 45203 | E58: FIA | F58: Convocatoria Nacional FIA 2023-2024 "Proyectos de Innovación en Sistemas Alimentarios Sostenibles" | G58: 16-Rayentué | H58: Diversificación floral con especies nativas y cultivos tradicionales con riego tecnificado, mejorando la disponibilidad de alimento en Apis melífera. | I58: Programa Nacional de Agrosistemas Sustentables | J58: CACERES CELEDON, EMILIO JOSE | K58: INIA | L58: No adjudicado | M58: 846 | N58: 45203 | O58: 149780815 | P58: 2500000 | Q58: 500000 | R58: 0 | S58: 64585123 | T58: =SUM(O58:S58) -> 217365938 | U58: 10200000 | W58: 48
A59: 5 | D59: =+Tabla2[[#This Row],[Fecha de Postulación]] -> 45168 | E59: FIC | F59: FIC O'Higgins 2023 | G59: 16-Rayentué | H59: Transferencia de soluciones técnicas para la recuperación de suelos en terrenos afectados por inundaciones y anegamiento, en las comunas de Coltauco y San Vicente, Región de O’Higgins | I59: Agrosistemas Sustentables | J59: CARRASCO JIMENEZ JORGE | K59: INIA | L59: No adjudicado | M59: 792 | N59: 45168 | O59: 209000000 | P59: 12300000 | R59: 0 | S59: 12258000 | T59: =SUM(O59:S59) -> 233558000
A60: 6 | C60: 2023 | D60: 45134 | E60: FIC | F60: FIC O'Higgins 2023 | G60: 16-Rayentué | H60: Transferencia tecnológica y revalorización de vides criollas y productos derivados con tradición patrimonial campesina para la Región de O'Higgins | I60: Producción Vegetal | J60: SAGREDO DIAZ, BORIS | K60: INIA | L60: Adjudicado | M60: 790 | N60: 45168 | O60: 186245345 | P60: 10500000 | Q60: 0 | R60: 0 | S60: 10501500 | T60: =SUM(O60:S60) -> 207246845 | U60: 9316000 | W60: 24 | Y60: Convenio TTT | AC60: IDI 40059068-0 | AE60: 186320000 | AF60: 10500000 | AG60: 10500001 | AH60: 186320000 | AI60: =+Tabla2[[#This Row],[Monto capturado po INIA]]+Tabla2[[#This Row],[Monto aporte INIA]]+Tabla2[[#This Row],[Monto contrapartida]] -> 207320001
A61: 7 | D61: 45260 | E61: FIC | F61: FIC O'Higgins 2023 | G61: 16-Rayentué | H61: Semillero colaborativo regional de variedades tradicionales INIA, en la comuna de San Vicente | I61: Producción Vegetal | J61: VEGA CANDIA, BARBARA CHANTAL | K61: INIA | L61: No adjudicado | M61: 789 | N61: 45168 | O61: 150000000 | P61: 15000000 | S61: 15531254 | T61: =SUM(O61:S61) -> 180531254 | W61: 36
A62: 8 | D62: 45626 | E62: FIC | F62: FIC O'Higgins 2023 | G62: 16-Rayentué | H62: Biofiltros domiciliarios para la utilización de aguas grises con riego tecnificado para la pequeña agricultura en las comunas de Pumanque, Paredones y Pichilemu. | I62: Agrosistemas Sustentables | J62: CACERES CELEDON, EMILIO JOSE | K62: INIA | L62: No adjudicado | M62: 788 | N62: 45168 | O62: 161900000 | P62: 9000000 | R62: 0 | S62: 8999000 | T62: =SUM(O62:S62) -> 179899000 | W62: 36
A63: 9 | D63: =+Tabla2[[#This Row],[Fecha de Postulación]] -> 45291 | E63: Contratos Privados Internacionales | F63: Otros concursos de alcance Internacional 2023 | G63: 16-Rayentué | H63: Diversificación de productos funcionales de quinua para contribuir a la seguridad alimentaria (FONTAGRO 2023 " Ciencia, Tecnología e Innovación para una Agricultura y Seguridad Alimentaria más Sostenible y Resiliente al Cambio Climático en América Latina y El Caribe") | I63: Producción Vegetal | J63: Félix Estrada | K63: UNAL - Universidad Nacional de Colombia- Colombia | L63: No adjudicado | M63: 785 | N63: 45291 | O63: 15347285 | P63: 0 | Q63: 0 | R63: 0 | S63: 34072981 | T63: =SUM(O63:S63) -> 49420266 | W63: 48
A64: 10 | D64: =+Tabla2[[#This Row],[Fecha de Postulación]] -> 45291 | E64: FONTAGRO | F64: 24 - Contratos privados internacionales | G64: 16-Rayentué | H64: Diversificación de productos funcionales de quinua para contribuir a la seguridad alimentaria (FONTAGRO 2023 " Ciencia, Tecnología e Innovación para una Agricultura y Seguridad Alimentaria más Sostenible y Resiliente al Cambio Climático en América Latina y El Caribe" | I64: Producción Vegetal | J64: ESTRADA BRAVO, FELIX RODOLFO | K64: INIA | L64: No adjudicado | M64: 785 | N64: 45291 | O64: 15347285 | P64: 0 | Q64: 0 | R64: 0 | S64: 34072981 | T64: =SUM(O64:S64) -> 49420266 | U64: 1534559 | V64: 0 | W64: 48
A65: 1 | D65: =+Tabla2[[#This Row],[Fecha de Postulación]] -> 45118 | E65: FIA | F65: Convocatoria Nacional Proyectos de Innovación-Interés Privado o Bienes Públicos- para el Agro 2023 (Propuesta completa) | G65: 16-Rayentué | H65: Desarrollo de un potencial agente antifúngico a partir de saponinas presentes en líneas avanzadas de quínoa | I65: Producción Vegetal | J65: Félix Estrada | K65: Tecnofen | L65: No adjudicado | M65: 755 | N65: 45118 | O65: 18162100 | P65: 0 | Q65: 0 | R65: 0 | S65: 25057753 | T65: =SUM(O65:S65) -> 43219853 | W65: 36
A66: 5 | D66: =+Tabla2[[#This Row],[Fecha de Postulación]] -> 45097 | E66: FONDECYT | F66: Regular | G66: 16-Rayentué | H66: Disentangling the epigenetic influence on differentiation of fruit development between early and late varieties in sweet cherry (Prunus avium) | I66: Producción Vegetal | J66: DONOSO CONTRERAS JOSE MANUEL | K66: Universidad de Chile | L66: No adjudicado | M66: 748 | N66: 45097 | O66: 21500000 | P66: 0 | Q66: 0 | R66: 0 | S66: 6727800 | T66: =SUM(O66:S66) -> 28227800 | W66: 48
A67: 6 | D67: =+Tabla2[[#This Row],[Fecha de Postulación]] -> 45050 | E67: ANID | F67: Anillos | G67: 16-Rayentué | H67: Plant Abiotic Stress tolerance for a Sustainable Agriculture (PASSA): Molecular Strategies for improving Plant Tolerance to drought and salinity | I67: Producción Vegetal | J67: MARTINEZ CASTILLO, JUAN PABLO | K67: Universidad de Chile | L67: No adjudicado | M67: 667 | N67: 45050 | O67: 86140000 | P67: 0 | Q67: 0 | R67: 103575 | S67: 0 | T67: =SUM(O67:S67) -> 86243575 | W67: 36
A68: 7 | C68: 2022 | D68: =+Tabla2[[#This Row],[Fecha de Postulación]] -> 44854 | E68: FIA | F68: Convocatoria Nacional FIA 2022-2023 "Proyectos de Innovación de Interés privado o Bienes Públicos para el Agro | G68: 16-Rayentué | H68: Plataforma interactiva para el desarrollo de mejoras en el control de plagas en cultivo de cítricos a través de la pulverización hidroneumática | I68: Agrosistemas Sustentables | J68: ABARCA REYES, LUIS PATRICIO | K68: INIA | L68: ADJUDICADO | M68: 609 | N68: 44854 | O68: 115159785 | P68: 6800000 | Q68: 0 | R68: 0 | S68: 37077338 | T68: =SUM(O68:S68) -> 159037123 | U68: 8040000 | V68: 0 | W68: 36 | X68: 17-04-2023, carta UPGN°23 del 26-04-2023 | Y68: Convenio TTT | AB68: Consejo Directivo FIA N° 240 | AC68: PYT 2023-0219 | AE68: 115159785 | AF68: 11224832 | AG68: 45186471 | AH68: 115159785 | AI68: =+AE68+AF68+Tabla2[[#This Row],[Monto aporte INIA]] -> 171571088
A69: 8 | C69: 2022 | D69: =+Tabla2[[#This Row],[Fecha de Postulación]] -> 44854 | E69: FIA | F69: Convocatoria Nacional FIA 2022-2023 "Proyectos de Innovación de Interés privado o Bienes Públicos para el Agro | G69: 16-Rayentué | H69: Nuevas estrategias de riego para el cultivo del nogal injertado sobre portainjertos clonales | I69: Producción Vegetal | J69: OTAROLA ALIAGA, JAIME IGNACIO | K69: INIA | L69: ADJUDICADO | M69: 593 | N69: 44854 | O69: 117487105 | P69: 0 | Q69: 7000000 | R69: 0 | S69: 59576551 | T69: =SUM(O69:S69) -> 184063656 | U69: 8200000 | V69: 0 | W69: 36 | X69: 17-04-2023, carta UPGN°243 del 26-04-2023 | Y69: Detalle en carta. Etapa de negociación | AB69: Consejo Directivo FIA N° 240 | AC69: PYT 2023-0259 | AE69: 119450000 | AF69: 2000000 | AG69: 70076551 | AH69: 0 | AI69: =+AE69+AF69+Tabla2[[#This Row],[Monto aporte INIA]] -> 191526551
A70: 9 | C70: 2022 | D70: =+Tabla2[[#This Row],[Fecha de Postulación]] -> 44776 | E70: FIC | F70: FIC | G70: 16-Rayentué | H70: Optimización de la aplicación de biocontroladores de origen microbiano a través de diferentes técnicas de pulverización en cultivos agrícolas de importancia para la Región de O'Higgins | I70: Producción Vegetal | J70: ABARCA REYES, LUIS PATRICIO | K70: INIA | L70: ADJUDICADO | M70: 493 | N70: 44776 | O70: 164103020 | P70: 0 | Q70: 871902 | R70: 12000000 | S70: 10974617 | T70: =SUM(O70:S70) -> 187949539 | U70: 8205151 | V70: 0 | W70: 36 | X70: 44974 | Y70: Etapa de firma de Convenio | AB70: Resolución Exenta N° 120 de fecha 17 de febrero de 2023 | AC70: Código IDI 40048423-0 | AE70: 164103020 | AF70: 23846519 | AG70: =+AF70 -> 23846519 | AH70: 0 | AI70: =+AE70+AF70 -> 187949539
A71: 10 | C71: 2022 | D71: =+Tabla2[[#This Row],[Fecha de Postulación]] -> 44776 | E71: FIC | F71: FIC | G71: 16-Rayentué | H71: Transferencia bioinmunizador endófito para el control de plagas y enfermedades en cucurbitáceas | I71: Agrosistemas Sustentables | J71: VEGA CANDIA, BARBARA CHANTAL | K71: INIA | L71: ADJUDICADO | M71: 487 | N71: 44776 | O71: 148500000 | P71: 0 | Q71: 0 | R71: 14400000 | S71: 13529712 | T71: =SUM(O71:S71) -> 176429712 | U71: 7425000 | V71: 0 | W71: 36 | X71: 44974 | Y71: Convenio TTT | AB71: Resolución Exenta N° 120 de fecha 17 de febrero de 2023 | AC71: 40048416-0 | AE71: 148500000 | AF71: 27929710 | AG71: =+AF71 -> 27929710 | AH71: 0 | AI71: =+AE71+AF71 -> 176429710
A72: 11 | C72: 2022 | D72: =+Tabla2[[#This Row],[Fecha de Postulación]] -> 44748 | E72: ANID | F72: FONDECYT Regular | G72: 16-Rayentué | H72: Caracterización e identificación de los factores genéticos de la resistencia al cáncer bacterial en cerezos (Prunus avium L.) presentes en cv Santina | I72: Producción Vegetal | J72: SAGREDO DIAZ, BORIS | K72: INIA | L72: ADJUDICADO | M72: 464 | N72: 44748 | O72: 319267521 | P72: 0 | Q72: 0 | R72: 0 | S72: 162709522 | T72: =SUM(O72:S72) -> 481977043 | U72: 0 | V72: 0 | W72: 48 | X72: 44992 | Y72: Convenio firmado | AB72: RESOLUCION EXENTO Nº: 3242/2023 del 06/04/2023 | AC72: 1231208 | AE72: 268800000 | AF72: 0 | AG72: 0 | AH72: 40800000 | AI72: =+AE72 -> 268800000
A73: 12 | C73: 2022 | D73: =+Tabla2[[#This Row],[Fecha de Postulación]] -> 44671 | E73: ANID | F73: Idea I&D | G73: 16-Rayentué | H73: Herramientas para determinar las características de la población del agente causal del cáncer bacterial en cerezos: Generando información clave para el desarrollo de estrategias sustentables de control | I73: Producción Vegetal | J73: SAGREDO DIAZ, BORIS | K73: INIA | L73: ADJUDICADO | M73: 418 | N73: 44671 | O73: 159156049 | P73: 0 | Q73: 24073545 | R73: 0 | S73: 57064535 | T73: =SUM(O73:S73) -> 240294129 | U73: 150000000 | V73: 0 | W73: 24 | X73: 44785 | AB73: RESOLUCION EXENTO Nº: 6968/2022 del 11/08/2022 | AC73: ID22I10318 | AE73: 160425000 | AF73: 24073545 | AG73: 94294747 | AH73: 15000000 | AI73: =+AE73+AF73+AG73 -> 278793292
A74: 1 | D74: =+Tabla2[[#This Row],[Fecha de Postulación]] -> 44644 | E74: FONDECYT | F74: Concurso de Proyectos Fondecyt de Iniciación en Investigación 2023 | G74: 16-Rayentué | H74: Effect of drought on the plasticity of physiological and agronomic traits in Lactuca sativa L. cultivars, under the context of climate change of southern Chile | I74: Producción Vegetal | J74: Félix Estrada | K74: iNIA | L74: No adjudicado | M74: 411 | N74: 44644 | O74: 14400000 | P74: 0 | Q74: 0 | R74: 0 | S74: 35949067 | T74: =SUM(O74:S74) -> 50349067 | W74: 36
A75: 2 | C75: 2021 | D75: =+Tabla2[[#This Row],[Fecha de Postulación]] -> 44428 | E75: FIA | F75: FIA Asignación Directa | G75: ='Perfiles '!D55 -> 16-Rayentué | H75: Programa de innovación en el uso eficiente del recurso hídrico para la pequeña agricultura de la región de O'Higgins | I75: Agrosistemas Sustentables | J75: FELMER ECHEVERRIA, SOFIA | K75: ='Perfiles '!H55 -> INIA | L75: ADJUDICADO | M75: 400 | N75: 44428 | O75: 85000000 | P75: 0 | Q75: 0 | R75: 850000 | S75: 55485807 | T75: =SUM(O75:S75) -> 141335807 | U75: 5950000 | V75: 0 | W75: 20 | X75: 44448 | Y75: en etapa negociación se deben corregir observaciones | Z75: N/A | AA75: N/A | AB75: Carta UDP-A-N°1831 de fecha 29/10/2021 Sesión Extraordinaria N°236, realizada el 27 de octubre de 2021. | AC75: PYT-2021-0661 | AE75: =O75 -> 85000000 | AF75: 0 | AG75: 56335807 | AH75: 0 | AI75: =AE75+AF75+AG75+AH75 -> 141335807
A76: 3 | C76: 2021 | D76: =+Tabla2[[#This Row],[Fecha de Postulación]] -> 44428 | E76: FIA | F76: FIA Asignación Directa | G76: ='Perfiles '!D56 -> 16-Rayentué | H76: Desarrollo de soluciones técnicas de manejo sustentable de suelos, agua y cultivos, para mejorar la situación post incendios forestales en predios de agricultores del área de secano de la región de O`Higgins y mitigar la problemática del cambio climático | I76: Agrosistemas Sustentables | J76: CARRASCO JIMENEZ JORGE | K76: ='Perfiles '!H56 -> INIA | L76: ADJUDICADO | M76: 395 | N76: 44428 | O76: 149985876 | P76: 6000000 | Q76: 9588000 | R76: 750000 | S76: 122918128 | T76: =SUM(O76:S76) -> 289242004 | U76: 10498010 | V76: 0 | W76: 36 | X76: 44448 | Y76: en etapa negociación se deben corregir observaciones | Z76: N/A | AA76: N/A | AB76: Carta UDP-A-N°1997 de fecha 24/11/2021 Sesión ordinaria N°274, realizada el 8 de septiembre de 2021. | AC76: PYT-2021-0639 | AE76: =O76 -> 149985876 | AF76: =P76 -> 6000000 | AG76: =R76+S76 -> 123668128 | AH76: 0 | AI76: =T76 -> 289242004
A77: 4 | D77: =+Tabla2[[#This Row],[Fecha de Postulación]] -> 44111 | E77: ANID | F77: I Concurso Nodos para la Aceleración de Impacto Territorial de la CTCI año 2020 | G77: 16-Rayentue, 20-Quilamapu | H77: Economía Circular y Sostenibilidad en los Procesos Industriales de la Macrozona Centro-Sur: Aseguramiento Agroalimentario | I77: Producción Vegetal | J77: SAGREDO DIAZ, BORIS | K77: U. Autonoma | L77: No adjudicado | M77: 127 | N77: 44111 | O77: 5280000 | P77: 0 | Q77: 0 | R77: 0 | S77: 9771240 | T77: =SUM(O77:S77) -> 15051240 | U77: 0 | V77: 0 | W77: 24 | X77: =L77 -> No adjudicado | Y77: N/A | Z77: 44167 | AB77: Rex 12375_2020 Adjudica I Concurso de Nodos CTCi
A78: 5 | D78: =+Tabla2[[#This Row],[Fecha de Postulación]] -> 44098 | E78: ANID | F78: Fondecyt de Postdoctorado 2021 | G78: 16-Rayentue | H78: Determination of root traits of durum wheat (Triticum turgidum L. spp. Durum) released from 1915 to 2015 to improve wheat grain yield in the Mediterranean dry land environments. | I78: Producción Vegetal | J78: ALFARO JARA, CHRISTIAN EUGENIO | K78: INIA | L78: No adjudicado | M78: 67 | N78: 44098 | O78: 81324000 | P78: 0 | Q78: 0 | R78: 0 | S78: 15000000 | T78: =SUM(O78:S78) -> 96324000 | U78: 0 | V78: 0 | W78: 36 | X78: =L78 -> No adjudicado | Y78: N/A | Z78: 44218 | AB78: Nomina adjudicados
D79: =+Tabla2[[#This Row],[Fecha de Postulación]] -> 44110 | E79: FIA | F79: Convocatoria Nacional de Proyectos 2020-2021 FIA | G79: 16-Rayentue | H79: Desarrollo y validación de un sistema automatizado de humidificación de alta presión como una herramienta multipropósito para el cultivo del cerezo bajo macrotúneles | I79: Producción Vegetal | J79: OTAROLA ALIAGA, JAIME IGNACIO | K79: INIA | L79: No adjudicado | M79: 64 | N79: 44110 | O79: 134590000 | P79: 10000000 | Q79: 12000000 | R79: 0 | S79: 41160395 | T79: =SUM(O79:S79) -> 197750395 | U79: 9400000 | V79: 0 | W79: 42 | X79: =L79 -> No adjudicado | Y79: N/A | Z79: 44218 | AB79: Nomina seleccionados y no seleccionados 2da etapa
D80: =+Tabla2[[#This Row],[Fecha de Postulación]] -> 44068 | E80: FIC | F80: FIC- Región del Maule | G80: 16-Rayentue, 20-Quilamapu | H80: Manejo del cáncer bacterial en huertos de cerezo de la Región del Maule a través de un control ecológicamente sustentable | I80: Producción Vegetal | J80: OTAROLA ALIAGA, JAIME IGNACIO | K80: INIA | L80: No adjudicado | M80: 42 | N80: 44068 | O80: 196528000 | P80: 20000000 | Q80: 7500000 | R80: 0 | S80: 80066715 | T80: =SUM(O80:S80) -> 304094715 | U80: 9800000 | V80: 0 | W80: 36 | X80: =L80 -> No adjudicado | Y80: N/A | Z80: 44081 | AA80: FF no da justificación, solo presenta listado de los aprobados para presentar a los CORES | AB80: N/A
C81: 2020 | D81: =+Tabla2[[#This Row],[Fecha de Postulación]] -> 44012 | E81: FIC | F81: FIC O'Higgins 2020 | G81: 16-Rayentue | H81: Ag Tech Invest Lab Innovation | I81: Agrosistemas Sustentables | J81: FELMER ECHEVERRIA, SOFIA | K81: INIA | L81: ADJUDICADO | M81: 23 | N81: 44012 | O81: 212000000 | P81: 12000000 | Q81: 0 | R81: 0 | S81: 18000000 | T81: =SUM(O81:S81) -> 242000000 | U81: 10000000 | V81: 0 | W81: 30 | X81: 44120 | Z81: N/A | AA81: N/A | AB81: Publicación Acuerdo CORE N°6.514 | AE81: 240000000 | AF81: 15000000 | AG81: 18000000 | AH81: 0 | AI81: =AE81+AF81+AG81 -> 273000000
C82: 2020 | D82: =+Tabla2[[#This Row],[Fecha de Postulación]] -> 44012 | E82: FIC | F82: FIC O'Higgins 2020 | G82: 16-Rayentue | H82: Transferencia hongos de la madera en frutales de carozo: situación actual y estrategias de control en la Región de O´Higgins. | I82: Producción Vegetal | J82: LEMUS SEPULVEDA, GAMALIER FDO | K82: INIA | L82: ADJUDICADO | M82: 22 | N82: 44012 | O82: 200000000 | P82: 12050000 | Q82: 0 | R82: 0 | S82: 27811000 | T82: =SUM(O82:S82) -> 239861000 | U82: 9650000 | V82: 0 | W82: 36 | X82: 44120 | Z82: N/A | AA82: N/A | AB82: Publicación Acuerdo CORE N°6.514 | AE82: 200000000 | AF82: 24275000 | AG82: 15536000 | AI82: =AE82+AF82+AG82 -> 239811000
D83: =+Tabla2[[#This Row],[Fecha de Postulación]] -> 44012 | E83: FIC | F83: FIC O'Higgins 2020 | G83: 16-Rayentue | H83: Transferencia Manejo hídrico eficiente en frutales para nueva zona de riego | I83: Producción Vegetal | J83: OTAROLA ALIAGA, JAIME IGNACIO | K83: INIA | L83: No adjudicado | M83: 21 | N83: 44012 | O83: 202780000 | P83: 15000000 | Q83: 0 | R83: 2433360 | S83: 30283000 | T83: =SUM(O83:S83) -> 250496360 | U83: 10000000 | V83: 0 | W83: 36 | X83: =L83 -> No adjudicado | Y83: N/A | Z83: 44120 | AA83: no se da justificación | AB83: Publicación Acuerdo CORE N°6.514
D84: =+Tabla2[[#This Row],[Fecha de Postulación]] -> 44019 | E84: ANID | F84: FONDECYT Regular 2021 | G84: 16-Rayentue | H84: HYDRAULIC MECHANISMS AND CARBON METABOLISM IN THE ADAPTATION OF DURUM WHEAT TO CONDITIONS OF CLIMATE CHANGE | I84: Producción Vegetal | J84: ALFARO JARA, CHRISTIAN EUGENIO | K84: UCH | L84: No adjudicado | M84: 12 | N84: 44019 | O84: 6265000 | P84: 0 | Q84: 0 | R84: 0 | S84: 25000000 | T84: =SUM(O84:S84) -> 31265000 | U84: 6265000 | V84: 0 | W84: 48 | X84: =L84 -> No adjudicado | Y84: N/A | Z84: 44218 | AB84: Nomina adjudicados
D85: =+Tabla2[[#This Row],[Fecha de Postulación]] -> 44019 | E85: ANID | F85: FONDECYT Regular 2021 | G85: 16-Rayentue | H85: Identification and development of molecular markers associated with genes responsible for the determination of sex in maqui (A. chilensis) and its location at chromosomal level. | I85: Producción Vegetal | J85: SAGREDO DIAZ, BORIS | K85: U. Autonoma Ch | L85: No adjudicado | N85: 44019 | O85: 15200000 | P85: 0 | Q85: 0 | R85: 0 | S85: 38635000 | T85: =SUM(O85:S85) -> 53835000 | U85: 15200000 | V85: 0 | W85: 48 | X85: =L85 -> No adjudicado | Y85: N/A | Z85: 44218 | AB85: Nomina adjudicados
D86: =+Tabla2[[#This Row],[Fecha de Postulación]] -> 44019 | E86: ANID | F86: FONDECYT Regular 2021 | G86: 16-Rayentue | H86: Identificación de factores genéticos y moleculares asociados a respuesta diferencial al cáncer bacterial en cerezos (Prunus avium L.) en grupos de variedades con resistencia contrastante | I86: Producción Vegetal | J86: SAGREDO DIAZ, BORIS | K86: INIA | L86: RECHAZADO | N86: 44019 | O86: 265600000 | P86: 0 | Q86: 0 | R86: 0 | S86: 146310000 | T86: =SUM(O86:S86) -> 411910000 | U86: 37600000 | V86: 0 | W86: 48 | X86: =L86 -> RECHAZADO | Y86: N/A | Z86: 44225 | AA86: fuera de bases por tener un informe pendiente de difusión en el proyecto Fondecyt 2018 cod. 502410. | AB86: Res. Ex. N°1590 | AC86: 1212020 | AD86: el investigador realizo una apelación
D87: =+Tabla2[[#This Row],[Fecha de Postulación]] -> 43755 | E87: FONDEF | F87: VIII Concurso de Investigación Tecnológica 2019-IDeA | G87: 10-La Platina, 16-Rayentue, 20-Quilamapu, 30-Carillanca | H87: Nuevas herramientas de monitoreo de poblaciones de Pseudomonas syringae agente causal del cáncer bacterial en cerezos para apoyar sistemas integrados de control y reducir contaminación con Cu+2. | I87: Producción Vegetal | J87: SAGREDO DIAZ, BORIS | K87: INIA | L87: RECHAZADO | N87: 43755 | O87: 229993000 | P87: 3240000 | Q87: 94800000 | R87: 0 | S87: 107555000 | T87: =SUM(O87:S87) -> 435588000 | U87: 26550000 | V87: 0 | W87: 24 | X87: =L87 -> RECHAZADO | Y87: N/A | Z87: 43847 | AA87: Impacto Potencial Económico Social Y sustentabilidad | AB87: Informe de Evaluación recibido por mail
D88: =+Tabla2[[#This Row],[Fecha de Postulación]] -> 43731 | E88: FIA | F88: Convocatoria Nacional Proyectos de Innovación 2019 FIA | G88: 16-RAYENTUE | H88: Bioinmunizador microbiano endófito para el manejo agroecológico de la cebolla como estrategia para disminuir el uso de agroquímicos en el cultivo. | I88: Agrosistemas Sustentables | J88: VEGA CANDIA, BARBARA CHANTAL | K88: INIA | L88: RECHAZADO | N88: 43731 | O88: 120700000 | P88: 2500000 | Q88: 0 | R88: 0 | S88: 68521024 | T88: =SUM(O88:S88) -> 191721024 | V88: 0 | W88: 48 | X88: =L88 -> RECHAZADO | Y88: N/A | Z88: 43914 | AA88: Solución planteada insuficiente | AB88: correo
D89: =+Tabla2[[#This Row],[Fecha de Postulación]] -> 43642 | E89: CONICYT | F89: XXIII Concurso Nacional de Proyectos Explora para elaboración de productos de divulgación de las ciencias y la tecnología 2019 2020 | G89: 16-RAYENTUE, 15-HIDANGO | H89: NATIVOAPP 2 0 Plataforma móvil y web para mapear e identificarflora nativa en Chile | I89: Producción Vegetal | J89: SAGREDO DIAZ, BORIS | K89: INIA | L89: RECHAZADO | N89: 43642 | O89: 30000000 | P89: 0 | Q89: 0 | R89: 0 | S89: 7500000 | T89: =SUM(O89:S89) -> 37500000 | U89: =O89 -> 30000000 | V89: 0 | W89: 12 | X89: RECHAZADO | Y89: N/A | Z89: 43754 | AA89: nota 4,09 no supera puntaje de corte 4,38 | AB89: Oficio N°350
D90: =+Tabla2[[#This Row],[Fecha de Postulación]] -> 43552 | E90: FONDEF | F90: CONCURSO IDEA I+D 2019 | G90: 16-RAYENTUE, 20-QUILAMAPU | H90: Plataforma de Información Epidemiologica para facilitar el control del Cáncer Bacterial en Cerezos | I90: Producción Vegetal | J90: SAGREDO DIAZ, BORIS | K90: INIA | L90: RECHAZADO | N90: 43552 | O90: 200000000 | P90: 0 | Q90: 51600000 | R90: 0 | S90: 86400000 | T90: =SUM(O90:S90) -> 338000000 | W90: 24 | X90: RECHAZADO | Y90: N/A | Z90: 43644 | AA90: Nota 2,6 | AB90: Informe de Evaluación recibido por mail | AC90: ID 19110375
D91: =+Tabla2[[#This Row],[Fecha de Postulación]] -> 43320 | E91: FIA | F91: Convocatoria Nacional Giras Nacionales para la Innovación de la Pequeña Agricultura 2018 | G91: 16-RAYENTUE | H91: Adquisición de conocimientos en el control biológico de plagas y enfermedades en las principales hortalizas de la región de O´higgins. | I91: Agrosistemas Sustentables | J91: VEGA CANDIA, BARBARA CHANTAL | K91: INIA | L91: RECHAZADO | N91: 43320 | O91: 2325000 | P91: 0 | Q91: 1053324 | R91: 3578324 | S91: 0 | T91: =SUM(O91:S91) -> 6956648 | X91: RECHAZADO | Y91: Carta FIA 2701 | Z91: 43355 | AA91: FF DECIDIO NO APROBAR
D92: =+Tabla2[[#This Row],[Fecha de Postulación]] -> 0 | E92: FONDECYT | F92: Otros Concursos de alcance nacional o regional 2018 | G92: 16-RAYENTUE | H92: Identificación de marcadores moleculares asociados a la determinación del sexo en maqui A chilensis y su ubicación a nivel cromosómico | I92: Producción Vegetal | J92: SAGREDO DIAZ, BORIS | K92: UNIVERSIDAD AUTONOMA | L92: RECHAZADO | O92: 41400000 | P92: 0 | Q92: 33900000 | R92: 76692000 | S92: 0 | T92: =SUM(O92:S92) -> 151992000 | W92: 48 | X92: RECHAZADO | Y92: CARTA RECIBIDA POR EL INVESTIGADOR PPAL | Z92: 43469 | AA92: POR C.V. DE LOS PROFESIONALES
D93: =+Tabla2[[#This Row],[Fecha de Postulación]] -> 0 | E93: FIA | F93: Otros Concursos de alcance nacional o regional 2018 | G93: 16-RAYENTUE | H93: Captura de conocimientos y experiencias en el manejo sustentable del cultivo del tomate | I93: Agrosistemas Sustentables | J93: VEGA CANDIA, BARBARA CHANTAL | K93: INIA | L93: RECHAZADO | O93: 4987260 | P93: 0 | Q93: 1672024 | R93: 6659284 | S93: 0 | T93: =SUM(O93:S93) -> 13318568 | X93: RECHAZADO | Y93: N/A | Z93: 43353
T94: =SUM(O94:S94) -> 0
T95: =SUM(O95:S95) -> 0
T96: =SUM(O96:S96) -> 0
T97: =SUM(O97:S97) -> 0
T98: =SUM(O98:S98) -> 0
T99: =SUM(O99:S99) -> 0
T100: =SUM(O100:S100) -> 0
T101: =SUM(O101:S101) -> 0
T102: =SUM(O102:S102) -> 0
T103: =SUM(O103:S103) -> 0
T104: =SUM(O104:S104) -> 0
T105: =SUM(O105:S105) -> 0
... T112: =SUM(O112:S112) -> 0

Sheet Pys Privados-12 y ADirecta Publ
M1: Monto contrapartida (asociados) | O1: Monto aporte INIA | R1: Monto capturado por INIA (Gastos de Administración) | AB1: Modificaciones al presupuesto solicitado
B2: Año Postulación | C2: Fuente Financiamiento | D2: Concurso o Linea | E2: CRI | F2: Titulo Proyecto | G2: Programas Nacionales | H2: Investigador/a Encargado/a | I2: Ejecutor Principal | J2: Estado | K2: Fecha de Postulación | L2: Monto solicitado | M2: Pecuniario | N2: No Pecuniario | O2: Pecuniario | P2: No Pecuniario | Q2: Costo Total del Proyecto | R2: Rendible a la FF | S2: Libre disposición (overhead) | T2: Duración (meses) | U2: Fecha de Aprobación | V2: Condiciones de aprobación | W2: Fecha de Rechazo | X2: Motivos rechazo | Y2: Fuente de Información (Acta resolución) | Z2: Codigo Proyecto Fuente financ. | AA2: Observaciones | AB2: Monto adjudicado | AC2: Monto contrapartida | AD2: Monto aporte INIA | AE2: Monto capturado po INIA | AF2: Costo Total del proyecto
B3: 2023 | C3: Municipalidad de Pichidegua | D3: Contrato Municipalidad | E3: 16-Rayentue | F3: Convenio de Colaboración Técnica y Transferencia Tecnológica INIA - Municipalidad de Pichidegua | G3: Producción Vegetal | H3: Bárbara Vega | I3: INIA | J3: Convenio firmado | K3: 45043 | L3: 5000000 | P3: 3442711 | Q3: =+L3+P3 -> 8442711 | R3: 0 | S3: 210084 | T3: 7 | U3: 45077
B4: 2025 | C4: Bioamerica | D4: CONTRATO PRIVADO | E4: 16-Rayentue | F4: CONTRATO DE PRESTACION DE SERVICIOS ENTRE INSTITUTO DE INVESTIGACIONES AGROPECUARIAS (INIA) Y BIOAMERICA S.A | G4: Producción Vegetal | H4: OTAROLA ALIAGA, JAIME IGNACIO | I4: INIA | J4: Convenio Firmado Inia | K4: 45689 | L4: 8901933 | P4: 8743845 | Q4: =+L4+P4 -> 17645778 | T4: 17
B5: 2023 | C5: Innovak Global Chile SpA | D5: CONTRATO PRIVADO | E5: 16-Rayentue | F5: Addendum Contrato de Trabajo | G5: Agrosistemas Sustentables | H5: CARRASCO JIMENEZ JORGE | I5: INIA | J5: Convenio firmado | K5: 44986 | L5: 10612500 | M5: 0 | N5: 0 | O5: 0 | P5: 14671736 | Q5: =SUM(L5:P5) -> 25284236 | R5: 0 | S5: 2540075 | T5: 10 | U5: 44986 | AA5: Renovación contrato
B6: 2024 | C6: Municipalidad de San Pedro | D6: Contrato Municipalidad | E6: 16-Rayentue | F6: Convenio de Colaboración INIA y Municipalidad de San Pedro Difusión de tecnologías de cultivos de trigo y triticale | G6: Producción Vegetal | H6: Cristian Aguirre | I6: INIA | J6: Convenio firmado | K6: 45565 | L6: 12000000 | Q6: =SUM(L6:P6) -> 12000000
B7: 2022 | C7: Municipalidad de San Pedro | D7: Contrato Municipalidad | E7: 16-Rayentue | F7: Convenio de Colaboración INIA y Municipalidad de San Pedro Difusión de tecnologías de cultivos de trigo y triticale | G7: Producción Vegetal | H7: Cristian Aguirre | I7: INIA | J7: Convenio firmado | K7: 44921 | L7: 10559833 | M7: 0 | N7: 0 | O7: 0 | P7: 1498447 | Q7: =SUM(L7:P7) -> 12058280 | R7: 0 | S7: 527991 | T7: 12 | U7: 44921
B8: 2022 | C8: NESTLÉ | D8: CONTRATO PRIVADO | E8: 16-Rayentue | F8: Implementación de prácticas de Agricultura Regenerativa en cultivos de trigo | G8: Producción Vegetal | H8: Christian Alfaro (cambia a Iván Matus de Quilamapu) | I8: INIA | J8: Convenio en revisión para firma | K8: 44805 | L8: 126000000 | M8: 0 | N8: 0 | O8: 0 | P8: 54427996 | Q8: =SUM(L8:P8) -> 180427996 | R8: 0 | S8: 17379000 | T8: 36 | U8: 44894
B9: 2022 | C9: Municipalidad San Vicente de Tagua Tagua | D9: Contrato Municipalidad | E9: 16-Rayentue | F9: Convenio de Asistencia Técnica y Transferencia Tecnológica INIA - San Vicente de Tagua Tagua | G9: Extensión y Formación de capacidades | H9: Bárbara Vega | I9: INIA | J9: Convenio firmado | K9: 44846 | L9: 21325500 | M9: 0 | N9: 0 | O9: 0 | P9: 7500000 | Q9: =SUM(L9:P9) -> 28825500 | R9: 1066275 | S9: 0 | T9: 15 | U9: 44846
B10: 2022 | C10: Municipalidad Quinta Tilcoco | D10: Contrato Municipalidad | E10: 16-Rayentue | F10: Programa GET Agroecológico de producción de hortalizas con inclusión de capacidades diferentes | G10: Extensión y Formación de capacidades | H10: Bárbara Vega | I10: INIA | J10: Convenio firmado | K10: 44708 | L10: 3444000 | M10: 0 | N10: 0 | O10: 0 | P10: 10126994 | Q10: =SUM(L10:P10) -> 13570994 | R10: 172000 | S10: 0 | T10: 12 | U10: 44748
B11: 2021 | C11: VIÑA LUIS FELIPE EDUARDS | D11: CONTRATO PRIVADO | E11: 16-Rayentue | F11: Evaluación Riego por pulso | G11: Agrosistemas Sustentables | H11: FELMER ECHEVERRIA, SOFIA | I11: INIA | J11: EN EVALUACION
B12: 2021 | C12: AGROSUPER | D12: CONTRATO PRIVADO | E12: 16-Rayentue | F12: evaluación de compost | G12: Agrosistemas Sustentables | H12: CARRASCO JIMENEZ JORGE | I12: INIA | J12: EN EVALUACION
B13: 2021 | C13: USACH | D13: CONTRATO PRIVADO | E13: 16-Rayentue | F13: Granos tradicionales para la seguridad alimentaria | G13: Producción Vegetal | H13: ALFARO JARA, CHRISTIAN EUGENIO | I13: USACH | J13: EN REDACCION DEL CONTRATO
B14: 2021 | C14: BIOAMERICA | D14: CONTRATO PRIVADO | E14: 16-Rayentue | F14: Efecto del producto ERGER 2 como quebrador de dormancia en cerezos (Prunus avium) var. Lapins | G14: Frutales | H14: OTAROLA ALIAGA, JAIME IGNACIO | I14: INIA | J14: APROBADO
B15: 2021 | C15: INNOVATEK | D15: CONTRATO PRIVADO | E15: 16-Rayentue | F15: evaluación del floculante de suelos Promesol 5X, | G15: Agrosistemas Sustentables | H15: CARRASCO JIMENEZ JORGE | I15: INIA | J15: APROBADO
B16: 2020 | C16: FIC | D16: CONTRATO PRIVADO | E16: 16-Rayentue | F16: Transferencia tecnológica PAFAM | G16: Producción Vegetal | H16: ALFARO JARA, CHRISTIAN EUGENIO | I16: UOH | J16: RECHAZADO | T16: 36 | U16: En concurso / paso Admisibilidad/ paso Ev Tecnica
B17: 2020 | C17: ASCC | D17: CONTRATO PRIVADO | E17: 16-Rayentue | F17: Programa APL Agroecología | G17: UPSE | H17: BARTEL CLAUDIA | I17: INIA | J17: EN POSTULACION CON V°B° FIC | L17: 151575000 | M17: 42666667
B18: 2020 | C18: Municipalidad Quinta Tilcoco | D18: CONTRATO PRIVADO | E18: 16-Rayentue | F18: GTT Agroecológico de Producción de Hortalizas con inclusión de capacidades diferentes | H18: VEGA BARBARA | I18: INIA | J18: APROBADO | L18: 2120842 | P18: 10920954 | AB18: 2120790

Sheet Analisis pymay25
A3: Añode adjudicación | B3: (Todas)
A5: Suma de Costo Total del Proyecto | B5: Etiquetas de columna
A6: Etiquetas de fila | B6: Adjudicado | C6: En Concurso | D6: No adjudicado | E6: OT | F6: RECHAZADO | G6: (en blanco) | H6: Total general
A7: Anid | B7: 767845544 | C7: 475886646 | D7: 282718815 | F7: 411910000 | H7: 1938361005
A8: ALFARO JARA, CHRISTIAN EUGENIO | D8: 127589000 | H8: 127589000
A9: MARTINEZ CASTILLO, JUAN PABLO | B9: 45574372 | C9: 475886646 | D9: 86243575 | H9: 607704593
A10: SAGREDO DIAZ, BORIS | B10: 722271172 | D10: 68886240 | F10: 411910000 | H10: 1203067412
A11: CONICYT | B11: 170280300 | F11: 66364000 | H11: 236644300
A12: ALFARO JARA, CHRISTIAN EUGENIO
A13: DONOSO CONTRERAS JOSE MANUEL | F13: 28864000 | H13: 28864000
A14: SAGREDO DIAZ, BORIS | B14: 170280300 | F14: 37500000 | H14: 207780300
A15: Contratos Privados Internacionales | D15: 49420266 | F15: 0 | H15: 49420266
A16: Félix Estrada | D16: 49420266 | H16: 49420266
A17: FELMER ECHEVERRIA, SOFIA | F17: 0 | H17: 0
A18: CORFO | D18: 174090817 | H18: 174090817
A19: OTAROLA ALIAGA, JAIME IGNACIO | D19: 174090817 | H19: 174090817
A20: FIA | B20: 773678590 | C20: 1107730381 | D20: 859501208 | F20: 191721024 | H20: 2932631203
A21: ABARCA REYES, LUIS PATRICIO | B21: 159037123 | C21: 211136880 | H21: 370174003
A22: CACERES CELEDON, EMILIO JOSE | D22: 461067026 | H22: 461067026
A23: CARRASCO JIMENEZ JORGE | B23: 289242004 | H23: 289242004
A24: Félix Estrada | D24: 43219853 | H24: 43219853
A25: FELMER ECHEVERRIA, SOFIA | B25: 141335807 | H25: 141335807
A26: MARTINEZ CASTILLO, JUAN PABLO | C26: 188863161 | H26: 188863161
A27: OTAROLA ALIAGA, JAIME IGNACIO | B27: 184063656 | C27: 410701484 | D27: 197750395 | H27: 792515535
A28: QUEZADA JARA, MARCELO | D28: 15000000 | H28: 15000000
A29: RUBILAR TORRES, FELIPE ANDRES | C29: 77243376 | H29: 77243376
A30: SAGREDO DIAZ, BORIS | D30: 142463934 | H30: 142463934
A31: VEGA CANDIA, BARBARA CHANTAL | F31: 191721024 | H31: 191721024
A32: DONOSO CONTRERAS, JOSE MANUEL | C32: 219785480 | H32: 219785480
A33: FIC | B33: 1053487096 | D33: 1148579329 | H33: 2202066425
A34: ABARCA REYES, LUIS PATRICIO | B34: 187949539 | H34: 187949539
A35: CACERES CELEDON, EMILIO JOSE | D35: 179899000 | H35: 179899000
A36: CARRASCO JIMENEZ JORGE | D36: 233558000 | H36: 233558000
A37: FELMER ECHEVERRIA, SOFIA | B37: 242000000 | H37: 242000000
A38: LEMUS SEPULVEDA, GAMALIER FDO | B38: 239861000 | H38: 239861000
A39: OTAROLA ALIAGA, JAIME IGNACIO | D39: 554591075 | H39: 554591075
A40: SAGREDO DIAZ, BORIS | B40: 207246845 | H40: 207246845
A41: VEGA CANDIA, BARBARA CHANTAL | B41: 176429712 | D41: 180531254 | H41: 356960966
A42: FNDR Antofagasta | B42: 1128650000 | H42: 1128650000
A43: VEGA CANDIA, BARBARA CHANTAL | B43: 1128650000 | H43: 1128650000
A44: FNDR O'Higgins | E44: 12285000 | H44: 12285000
A45: BARTEL CLAUDIA | E45: 12285000 | H45: 12285000
A46: FONDECYT | C46: 605721942 | D46: 973444353 | H46: 1579166295
A47: ALFARO JARA, CHRISTIAN EUGENIO
A48: DONOSO CONTRERAS JOSE MANUEL | D48: 381927318 | H48: 381927318
A49: ESTRADA BRAVO, FELIX RODOLFO | C49: 167467518 | D49: 111227528 | H49: 278695046
A50: Félix Estrada | D50: 50349067 | H50: 50349067
A51: MARTINEZ CASTILLO, JUAN PABLO | C51: 420163718 | D51: 429940440 | H51: 850104158
A52: SAGREDO DIAZ, BORIS
A53: DONOSO CONTRERAS, JOSE MANUEL | C53: 18090706 | H53: 18090706
A54: FONDEF | C54: 419129265 | F54: 1061385000 | H54: 1480514265
A55: OTAROLA ALIAGA, JAIME IGNACIO | F55: 287797000 | H55: 287797000
A56: SAGREDO DIAZ, BORIS | C56: 419129265 | F56: 773588000 | H56: 1192717265
A57: FONDEQUIP | B57: 120627400 | H57: 120627400
A58: SAGREDO DIAZ, BORIS | B58: 120627400 | H58: 120627400
A59: FRPD | C59: 1643525548 | H59: 1643525548
A60: QUEZADA JARA, MARCELO | C60: 316085437 | H60: 316085437
A61: RUBILAR TORRES, FELIPE ANDRES | C61: 224302390 | H61: 224302390
A62: VEGA CANDIA, BARBARA CHANTAL | C62: 297896617 | H62: 297896617
A63: ALTIMIRA PASSALACQUA, FABIOLA | C63: 372566598 | H63: 372566598
A64: RIQUELME TOLEDO, DANAE | C64: 432674506 | H64: 432674506
A65: INNOVA-CORFO | F65: 139047000 | H65: 139047000
A66: OTAROLA ALIAGA, JAIME IGNACIO | F66: 139047000 | H66: 139047000
A67: FONTAGRO | D67: 49420266 | H67: 49420266
A68: ESTRADA BRAVO, FELIX RODOLFO | D68: 49420266 | H68: 49420266
A69: (en blanco)
A70: (en blanco)
A71: Año Postulación2 | B71: (Varios elementos)
B73: Etiquetas de columna
B74: En Concurso | D74: Total Cuenta de Titulo Proyecto | E74: Total Suma de Monto solicitado
A75: Etiquetas de fila | B75: Cuenta de Titulo Proyecto | C75: Suma de Monto solicitado
A76: Anid | B76: 1 | C76: 227654080 | D76: 1 | E76: 227654080
A77: MARTINEZ CASTILLO, JUAN PABLO | B77: 1 | C77: 227654080 | D77: 1 | E77: 227654080
A78: FIA | B78: 1 | C78: 119808000 | D78: 1 | E78: 119808000
A79: OTAROLA ALIAGA, JAIME IGNACIO | B79: 1 | C79: 119808000 | D79: 1 | E79: 119808000
A80: FONDECYT | B80: 1 | C80: 104400000 | D80: 1 | E80: 104400000
A81: ESTRADA BRAVO, FELIX RODOLFO | B81: 1 | C81: 104400000 | D81: 1 | E81: 104400000
A82: FONDEF | B82: 1 | C82: 237000000 | D82: 1 | E82: 237000000
A83: SAGREDO DIAZ, BORIS | B83: 1 | C83: 237000000 | D83: 1 | E83: 237000000
A84: FRPD | B84: 5 | C84: 1300452408 | D84: 5 | E84: 1300452408
A85: ALTIMIRA PASSALACQUA, FABIOLA | B85: 1 | C85: 280000000 | D85: 1 | E85: 280000000
A86: QUEZADA JARA, MARCELO | B86: 1 | C86: 280000000 | D86: 1 | E86: 280000000
A87: RIQUELME TOLEDO, DANAE | B87: 1 | C87: 280000000 | D87: 1 | E87: 280000000
... A90: Total general | B90: 9 | C90: 1989314488 | D90: 9 | E90: 1989314488

Sheet Analisis perfiles may 25
A2: AÑO | B2: (Varios elementos)
A3: ID- Perfil | B3: (Todas)
A5: Cuenta de TÍTULO | B5: Etiquetas de columna
A6: Etiquetas de fila | B6: Adjudicado | C6: No Adjudicado | D6: No Postulado | E6: Postulado | F6: Total general
A7: ABARCA REYES, LUIS PATRICIO | D7: 1 | E7: 1 | F7: 2
A8: Atimira Passalacqua Fabiola | B8: 1 | F8: 1
A9: CACERES CELEDON, EMILIO JOSE | C9: 1 | F9: 1
A10: DONOSO CONTRERAS, JOSE MANUEL | C10: 2 | E10: 2 | F10: 4
A11: ESTRADA BRAVO, FELIX RODOLFO | C11: 1 | E11: 1 | F11: 2
A12: MARTINEZ CASTILLO, JUAN PABLO | C12: 1 | D12: 1 | E12: 3 | F12: 5
A13: OTAROLA ALIAGA, JAIME IGNACIO | B13: 1 | C13: 1 | E13: 1 | F13: 3
A14: QUEZADA JARA, MARCELO | B14: 1 | C14: 1 | F14: 2
A15: Riquelme Toledo Danae | B15: 1 | F15: 1
A16: RUBILAR TORRES, FELIPE ANDRES | B16: 1 | E16: 1 | F16: 2
A17: SAGREDO DIAZ, BORIS | C17: 1 | F17: 1
A18: VEGA CANDIA, BARBARA CHANTAL | C18: 1 | F18: 1
A19: Total general | B19: 5 | C19: 9 | D19: 2 | E19: 9 | F19: 25

Sheet JC PErfiles
C2: Investigador | D2: Adjudicado | E2: No Adjudicado | F2: En Concurso | G2: Total general
C3: ABARCA REYES, LUIS PATRICIO | D3: 2 | G3: =+D3+E3+F3 -> 2
C4: Atimira Passalacqua Fabiola | F4: 1 | G4: =+D4+E4+F4 -> 1
C5: CACERES CELEDON, EMILIO JOSE | E5: 3 | G5: =+D5+E5+F5 -> 3
C6: CARRASCO JIMENEZ JORGE | E6: 1 | G6: =+D6+E6+F6 -> 1
C7: DONOSO CONTRERAS, JOSE MANUEL | E7: 3 | G7: =+D7+E7+F7 -> 3
C8: ESTRADA BRAVO, FELIX RODOLFO | E8: 5 | F8: 1 | G8: =+D8+E8+F8 -> 6
C9: MARTINEZ CASTILLO, JUAN PABLO | D9: 1 | E9: 2 | F9: 1 | G9: =+D9+E9+F9 -> 4
C10: OTAROLA ALIAGA, JAIME IGNACIO | D10: 1 | E10: 1 | F10: 1 | G10: =+D10+E10+F10 -> 3
C11: QUEZADA JARA, MARCELO | E11: 1 | F11: 1 | G11: =+D11+E11+F11 -> 2
C12: Riquelme Toledo Danae | F12: 1 | G12: =+D12+E12+F12 -> 1
C13: RUBILAR TORRES, FELIPE ANDRES | F13: 1 | G13: =+D13+E13+F13 -> 1
C14: SAGREDO DIAZ, BORIS | D14: 3 | F14: 1 | G14: =+D14+E14+F14 -> 4
C15: VEGA CANDIA, BARBARA CHANTAL | D15: 1 | E15: 1 | F15: 1 | G15: =+D15+E15+F15 -> 3
C16: Total general | D16: 8 | E16: 17 | F16: 9 | G16: =SUM(G3:G15) -> 34
C35: Adjudicado | E35: En Concurso | G35: No adjudicado
B36: Fuente de Financiamiento | C36: Cant. Proyecto | D36: Monto solicitado | E36: Cant. Proyecto | F36: Monto solicitado | G36: Cant. Proyecto | H36: Monto solicitado
B37: ANID | C37: 3 | D37: 523997942 | E37: 1 | F37: 227654080 | G37: 1 | H37: 86140000
B38: Contratos Internacionales | G38: 1 | H38: 15347285
B39: CORFO | G39: 1 | H39: 103327093
B40: FIA | C40: 2 | D40: 232646890 | E40: 1 | F40: 119808000 | G40: 4 | H40: 329942915
B41: FIC | C41: 3 | D41: 498848365 | G41: 3 | H41: 520900000
B42: FONDECYT | E42: 1 | F42: 104400000 | G42: 6 | H42: 644664533
B43: FONDEF | E43: 1 | F43: 237000000
B44: FONTAGRO | G44: 1 | H44: 15347285
B45: FRPD | E45: 5 | F45: 1300452408
B46: Total general | C46: 8 | D46: 1255493197 | E46: 9 | F46: 1989314488 | G46: 17 | H46: 1715669111
C55: Etiquetas de fila | D55: Postulado | E55: Total general
C56: Concurso de Investigación Tecnológica IDeA 2025 | D56: 1 | E56: 1 | G56: Proyectos en Concurso | H56: Proyectos | I56: Monto $
C57: SAGREDO DIAZ, BORIS | D57: 1 | E57: 1 | G57: ANID | H57: 1 | I57: 227654080
C58: Convocatoria Nacional Proyectos de Innovación para el agro con Énfasis Regional 2024-2025 FIA | D58: 1 | E58: 1 | G58: MARTINEZ CASTILLO, JUAN PABLO | H58: 1 | I58: 227654080
C59: OTAROLA ALIAGA, JAIME IGNACIO | D59: 1 | E59: 1 | G59: FIA | H59: 1 | I59: 119808000
C60: Fondecyt de Iniciación en Investigación 2026 | D60: 1 | E60: 1 | G60: OTAROLA ALIAGA, JAIME IGNACIO | H60: 1 | I60: 119808000
C61: ESTRADA BRAVO, FELIX RODOLFO | D61: 1 | E61: 1 | G61: FONDECYT | H61: 1 | I61: 104400000
C62: Fondo Regional para la Productividad y el Desarrollo (FRPD)- Región de O'Higgins 2024 | D62: 5 | E62: 5 | G62: ESTRADA BRAVO, FELIX RODOLFO | H62: 1 | I62: 104400000
C63: Atimira Passalacqua Fabiola | D63: 1 | E63: 1 | G63: FONDEF | H63: 1 | I63: 237000000
C64: QUEZADA JARA, MARCELO | D64: 1 | E64: 1 | G64: SAGREDO DIAZ, BORIS | H64: 1 | I64: 237000000
C65: Riquelme Toledo Danae | D65: 1 | E65: 1 | G65: FRPD | H65: 5 | I65: 1300452408
C66: RUBILAR TORRES, FELIPE ANDRES | D66: 1 | E66: 1 | G66: ALTIMIRA PASSALACQUA, FABIOLA | H66: 1 | I66: 280000000
C67: VEGA CANDIA, BARBARA CHANTAL | D67: 1 | E67: 1 | G67: QUEZADA JARA, MARCELO | H67: 1 | I67: 280000000
C68: IDeA I+D 2025 | D68: 1 | E68: 1 | G68: RIQUELME TOLEDO, DANAE | H68: 1 | I68: 280000000
... C70: Total general | D70: 9 | E70: 9 | G70: VEGA CANDIA, BARBARA CHANTAL | H70: 1 | I70: 256543408
G71: Total general | H71: 9 | I71: 1989314488

Sheet Datos
A2: Postulado
A3: Adjudicado
A4: Rechazado
A5: No admitido

Sheet Perfiles data
C1: FECHA ACTUALIZACIÓN | D1: 45199
C2: RESPONSABLE | D2: ='Pys Post.'!F10:G10 -> #VALUE!
B3: AÑO | C3: CONCURSO O LINEA | D3: CRI | E3: TÍTULO | F3: Programas Nacionales | G3: Investigador/a Encargado/a | H3: Ejecutor Principal | I3: Estado Perfil | J3: Postulado | K3: Adjudicado | L3: Comentarios
B4: 20 de feb 16:52 | C4: Concurso de Investigación Tecnológica IDeA 2025 | D4: 16-Rayentué | E4: GENERANDO INFORMACIÓN CLAVE PARA EL DESARROLLO DE ESTRATEGIAS SUSTENTABLES DE CONTROL DEL CANCER BACTERIAL EN CEREZOS: BASADOS EN LAS CARACTERÍSTICAS DE LA POBLACIÓN DEL AGENTE CAUSAL | F4: Producción Vegetal | G4: SAGREDO DIAZ, BORIS | H4: INIA | I4: Postulado
B5: 45606 | C5: Convocatoria Nacional Proyectos de Innovación para el agro con Énfasis Regional 2024-2025 FIA | D5: 16-Rayentué | E5: Desarrollo de estrategias de riego deficitario controlado en diferentes variedades de cerezos y zonas agroclimáticas de Chile con baja disponibilidad hídrica. | F5: Programa Nacional de Agrosistemas Sustentables | G5: CACERES CELEDON, EMILIO JOSE | H5: INIA | I5: No Adjudicado
B6: 45606 | C6: Convocatoria Nacional Proyectos de Innovación para el agro con Énfasis Regional 2024-2025 FIA | D6: 16-Rayentué | E6: Empaquetamiento técnico y comercial de la primera variedad de cereza chilena para un mercado de alta exigencia en calidad | F6: Producción Vegetal | G6: OTAROLA ALIAGA, JAIME IGNACIO | H6: INIA | I6: Postulado
B7: 45581 | C7: Fondo Regional para la Productividad y el Desarrollo (FRPD)- Región de O'Higgins 2024 | D7: 16-Rayentué | E7: Desarrollo de la agricultura urbana y periurbana como alternativa de desarrollo sostenible para la producción de alimentos en la Región de O`Higgins. | F7: Programa Nacional de Agrosistemas Sustentables | G7: RUBILAR TORRES, FELIPE ANDRES | H7: INIA | I7: Postulado
B8: 45581 | C8: Fondo Regional para la Productividad y el Desarrollo (FRPD)- Región de O'Higgins 2024 | D8: 16-Rayentué | E8: OptiVol: Una plataforma digital para la optimización de la pulverización hidroneumática utilizada en frutales de hoja caduca | F8: Programa Nacional de Agrosistemas Sustentables | G8: ABARCA REYES, LUIS PATRICIO | H8: INIA | I8: No Postulado
B9: 45581 | C9: Fondo Regional para la Productividad y el Desarrollo (FRPD)- Región de O'Higgins 2024 | D9: 16-Rayentué | E9: Transferencia de un paquete tecnológico para el control de ataques de depredadores en ovinos del secano costero de O’Higgins. | F9: Programa Nacional de Producción Animal | G9: QUEZADA JARA, MARCELO | H9: INIA | I9: Postulado
B10: 45576 | C10: Fondo Regional para la Productividad y el Desarrollo (FRPD)- Región de O'Higgins 2024 | D10: 16-Rayentué | E10: Biofábricas en la región de O´Higgins, una alternativa a la producción de agroinsumos con visión agroecológica | F10: Programa Nacional de Agrosistemas Sustentables | G10: VEGA CANDIA, BARBARA CHANTAL | H10: INIA | I10: Postulado
B11: 5 de agosto de 2024 11:18 | C11: Red de Fomento Sostenible-1º Convocatoria 2024-Sector Agricultura | D11: 16-Rayentué | E11: “RedFrutiT: Red de innovación tecnológica para una fruticultura sustentable y resiliente en Chile” (Red de Fomento Sostenible-1º Convocatoria 2024-Sector Agricultura) | F11: Producción Vegetal | G11: OTAROLA ALIAGA, JAIME IGNACIO | H11: UC DAVIS CHILE - FUNDACION UC DAVIS CHILE LIFE SCIENCES INNOVATION CENTER | I11: Postulado | L11: Se ha solicitado por correo los papeles a la ejecutora principal para cerrar el proceso ya que se sabe que no fue adjudicado
B12: 31 de julio de 2024 16:57 | C12: IDeA I+D 2025 | D12: 16-Rayentué | E12: Desarrollo de un sistema de producción de plantas de tomate injertadas sobre portainjertos clonales originados por cruzamientos interespecíficos (S. lycopersicum x S. chilense) para mejorar la productividad y calidad de tomate fresco. | F12: Producción Vegetal | G12: MARTINEZ CASTILLO, JUAN PABLO | H12: INIA | I12: Postulado
B13: 4 de junio de 2024 09:25 | C13: Fondecyt Regular 2025 | D13: 16-Rayentué | E13: Improving salt tolerance of “Old Limachino Tomato” by using two clonal rootstocks issued from interspecific reciprocal crosses between wild and cultivated tomato, with different level of salt tolerance. | F13: Producción Vegetal | G13: MARTINEZ CASTILLO, JUAN PABLO | H13: INIA | I13: No Adjudicado
B14: 29 de mayo de 2024 15:11 | C14: Fondecyt Regular 2025 | D14: 16-Rayentué | E14: Disentangling the epigenetic influence on differentiation of fruit development between early and late varieties in sweet cherry (Prunus avium) (FONDECYT REGULAR) | F14: Producción Vegetal | G14: DONOSO CONTRERAS, JOSE MANUEL | H14: INIA | I14: No Adjudicado
B15: 25 de mayo de 2024 20:35 | C15: Fondecyt Regular 2025 | D15: 16-Rayentué | E15: Understanding the genetics related to orange peel disorder in sweet cherry (Prunus avium L.) | F15: Producción Vegetal | G15: DONOSO CONTRERAS, JOSE MANUEL | H15: INIA | I15: No Adjudicado
B16: 17 de abril de 2024 09:01 | C16: Convocatoria Nacional Proyectos de Innovación-Interés Privado o Bienes Públicos- para el Agro 2024 (Propuesta completa) | D16: 16-Rayentué | E16: Desarrollo de un paquete agronómico para una línea avanzada de cerezo adaptada al cambio climático: la primera variedad de la especie creada 100% en Chile | F16: Producción Vegetal | G16: DONOSO CONTRERAS, JOSE MANUEL | H16: INIA | I16: No Seleccionado
B17: 15 de abril de 2024 10:53 | C17: Fondecyt de Iniciación en Investigación 2025 | D17: 16-Rayentué | E17: A comprehensive analysis of the phenotypic plasticity of key traits for selecting quinoa genotypes (Chenopodium quinoa Willd.) under contrasting environments | F17: Producción Vegetal | G17: ESTRADA BRAVO, FELIX RODOLFO | H17: INIA | I17: No Adjudicado
B18: 45366 | C18: Instrumentos Complementarios FIA: Giras Nacionales para la Innovación 2024 | D18: 16-Rayentué | E18: Visita a experiencias de cooperativas exitosas en la Región de Los Lagos, con productores ovinos del secano costero de la Región de O'Higgins. | F18: Programa Nacional de Producción Animal | G18: QUEZADA JARA, MARCELO | H18: INIA | I18: No Adjudicado
B19: 45272 | C19: Crea y Valida Foco en Sostenibilidad 2023 | D19: 16-Rayentué | E19: Desarrollo de un agente antifúngico a partir de saponinas presentes en líneas avanzadas de quínoas chilenas | F19: Producción Vegetal | G19: ESTRADA BRAVO, FELIX RODOLFO | H19: TECNOLOGIA EN FENOMICA DE PLANTAS LIMITADA | I19: No Seleccionado
B20: 45231 | C20: Concurso Startup Ciencia 2024 (2º llamado 2023) | D20: 16-Rayentué | E20: Desarrollo de un sensor portátil (Optiriego) que optimiza el manejo de riego en tomates y uva vinífera | F20: Producción Vegetal | G20: Juan Pablo Martínuez | H20: YUMMY FRUIT SPA | I20: Adjudicado | J20: Si | K20: Si
B21: 45200 | C21: Convocatoria Nacional FIA 2023-2024 "Proyectos de Innovación en Sistemas Alimentarios Sostenibles" | D21: 16-Rayentué | E21: Diversificación floral con especies nativas y cultivos tradicionales con riego tecnificado, mejorando la disponibilidad de alimento en Apis melífera. | F21: Agrosistemas Sustentables | G21: Emilio Cáceres | H21: INIA | I21: No Adjudicado | J21: Si | K21: No | L21: Comunicación no pertinente 09-11-2023
B22: 45108 | C22: FIC O'Higgins 2023 | D22: 16-Rayentué | E22: Transferencia tecnológica y revalorización de vides criollas y productos derivados con tradición patrimonial campesina para la Región de O'Higgins | F22: Producción Vegetal | G22: Boris Sagredo | H22: INIA | I22: Adjudicado | J22: Si | K22: Si | L22: Comunicación de adjudicación 14-11-2023
B23: 45108 | C23: FIC O'Higgins 2023 | D23: 16-Rayentué | E23: Semillero colaborativo regional de variedades tradicionales INIA, en la comuna de San Vicente | F23: Producción Vegetal | G23: Bárbara Vega | H23: INIA | I23: No Adjudicado | J23: Si | K23: No
B24: 45108 | C24: FIC O'Higgins 2023 | D24: 16-Rayentué | E24: Desarrollo de soluciones técnicas para la recuperación de suelos y cultivos en terrenos afectados por desborde de ríos e inundaciones, en la pequeña y mediana agricultura en las comunas de Coltauco y San Vicente, Región de O’Higgins | F24: Agrosistemas Sustentables | G24: Jorge Carrasco | H24: INIA | I24: No adjudicado | J24: Si | K24: No | L24: No admitido por bases (faltó documentación)
B25: 45108 | C25: FIC O'Higgins 2023 | D25: 16-Rayentué | E25: Biofiltros domiciliarios para la utilización de aguas grises con riego tecnificado para la pequeña agricultura en las comunas de Pumanque, Navidad y Pichilemu | F25: Agrosistemas Sustentables | G25: Emiio Cáceres | H25: INIA | I25: No Adjudicado | J25: Si | K25: No | L25: No admitido por bases (faltó documentación)
B26: 45108 | C26: FONTAGRO 2023 | D26: 16-Rayentué | E26: Diversificación de productos funcionales de quinua para contribuir a la seguridad alimentaria | F26: Producción Vegetal | G26: Félix Estrada | H26: UNAL - Universidad Nacional de Colombia- Colombia | I26: No Adjudicado | J26: Si
B27: 45108 | C27: FIA | D27: 16-Rayentué | E27: Desarrollo de un potencial agente antifúngico a partir de saponinas presentes en líneas avanzadas de quínoa | F27: Producción Vegetal | G27: Félix Estrada | H27: Tecnofen | I27: No Adjudicado | J27: Si
B28: 45078 | C28: FONDECYT 2024 | D28: 16-Rayentué | E28: Disentangling the epigenetic influence on differentiation of fruit development between early and late varieties in sweet cherry (Prunus avium) | F28: Producción Vegetal | G28: José Manuel Donoso | H28: Universidad de Chile | I28: No Adjudicado | J28: Si
B29: 45047 | C29: Anillos de Investigación en Áreas Temáticas Específicas 2023 | D29: 16-Rayentué | E29: Plant Abiotic Stress tolerance for a Sustainable Agriculture (PASSA): Molecular Strategies for improving Plant Tolerance to drought and salinity | F29: Producción Vegetal | G29: Juan Pablo Martínez | H29: Universidad de Chile | I29: No Adjudicado | J29: Si | K29: No
B30: 44987 | C30: Concurso de Investigación Tecnológica IDeA 2023 (apertura 2022) | D30: 16-Rayentué | E30: Validación en huertos comerciales de selecciones avanzadas de cerezos de distintos programas de mejoramiento genético de Chile y del extranjero | F30: Producción Vegetal | G30: José Manuel Donoso | H30: Universidad de Talca | I30: No Seleccionado | J30: NO | K30: NO
B31: 45017 | C31: FONDECYT Iniciación 2024 | D31: 16-Rayentué | E31: A comprehensive characterization of physiological and agronomic traits for detecting keystones to select quinoa (Chenopodium quinoa Willd.) genotypes under adverse environments | F31: Producción Vegetal | G31: Félix Estrada | H31: INIA | I31: No Adjudicado | J31: Si
B32: 44835 | C32: FIA 2022-2023 | D32: 16-Rayentué | E32: Caracterización y evaluación de suelos de predios de la pequeña agricultura para su incorporación a la producción de rubros de mayor rentabilidad como la fruticultura y horticultura | F32: Agrosistemas Sustentables | G32: Jorge Carrasco | H32: INIA | I32: Perfil no Seleccionado | J32: No
B33: 44835 | C33: FIA 2022-2023 | D33: 16-Rayentué | E33: Control y prevención de los incendios forestales con ovinos para mitigar los efectos del cambio climático. | F33: Producción Animal | G33: Marcelo Quezada | H33: INIA | I33: Perfil no Seleccionado | J33: No
B34: 44835 | C34: FIA 2022-2023 | D34: 16-Rayentué | E34: Plataforma interactiva para el desarrollo de mejoras en el control de plagas en cultivo de cítricos a través de la pulverización hidroneumática | F34: Agrosistemas Sustentables | G34: Patricio Abarca | H34: INIA | I34: Adjudicado | J34: Si | K34: Si | L34: Aprobado
B35: 44835 | C35: FIA 2022-2023 | D35: 16-Rayentué | E35: Nuevas estrategias de riego para el cultivo del nogal injertado sobre portainjertos clonales | F35: Producción Vegetal | G35: Jaime Otárola | H35: INIA | I35: Perfil Seleccionado | J35: Si | K35: Si | L35: Aprobado
B36: 44774 | C36: FIC | D36: 16-Rayentué | E36: Optimización de la aplicación de biocontroladores de origen microbiano a través de diferentes técnicas de pulverización en cultivos agrícolas de importancia para la Región de O'Higgins | F36: Producción Vegetal | G36: Patricio Abarca | H36: INIA | I36: Adjudicado | J36: Si | K36: Si | L36: Aprobado
B37: 44774 | C37: FIC | D37: 16-Rayentué | E37: Transferencia bioinmunizador endófito para el control de plagas y enfermedades en cucurbitáceas | F37: Agrosistemas Sustentables | G37: Bárbara Vega | H37: INIA | I37: Adjudicado | J37: Si | K37: Si | L37: Aprobado
B38: 44774 | C38: FIC | D38: 16-Rayentué | E38: Transferencia de la caracterización y evaluación de suelos de predios de la pequeña agricultura para su incorporación a la producción de rubros de mayor rentabilidad como la fruticultura y horticultura | F38: Agrosistemas Sustentables | G38: Jorge Carrasco | H38: INIA | I38: Seleccionado con condiciones | J38: No | L38: No postulado por imposibilidad de gestionar recursos pecuniarios de contrapartida en el monto que haga viable la propuesta.
B39: 44743 | C39: FONDECYT Regular | D39: 16-Rayentué | E39: Caracterización e identificación de los factores genéticos de la resistencia al cáncer bacterial en cerezos (Prunus avium L.) presentes en cv Santina | F39: Producción Vegetal | G39: Boris Sagredo | H39: INIA | I39: Adjudicado | J39: Si | K39: APROBADO
B40: 44599 | C40: FONDECYT Iniciación 2024 | D40: 16-Rayentué | E40: Effect of drought on the plasticity of physiological and agronomic traits in Lactuca sativa L. cultivars, under the context of climate change of southern Chile | F40: Producción Vegetal | G40: ESTRADA BRAVO, FELIX RODOLFO | H40: INIA | I40: No Adjudicado | J40: Si | K40: RECHAZADO
B41: 44652 | C41: ANID Idea I&D | D41: 16-Rayentué | E41: Herramientas para determinar las características de la población del agente causal del cáncer bacterial en cerezos: Generando información clave para el desarrollo de estrategias sustentables de control | F41: Producción Vegetal | G41: Boris Sagredo | H41: INIA | I41: Adjudicado | J41: Si | K41: APROBADO
A42: 1 | B42: 44496 | C42: FIA Asignacion Directa | D42: 16-Rayentue | E42: Programa de innovación en el uso eficiente del recurso hídrico para la pequeña agricultura de la región de O'Higgins | F42: Agrosistemas Sustentables | G42: FELMER ECHEVERRIA, SOFIA | H42: INIA | I42: Adjudicado | J42: SI | K42: APROBADO
A43: 2 | B43: 44428 | C43: FIA Asignacion Directa | D43: 16-Rayentue | E43: Desarrollo de soluciones técnicas de manejo sustentable de suelos, agua y cultivos, para mejorar la situación post incendios forestales en predios de agricultores del área de secano de la región de O`Higgins y mitigar la problemática del cambio climático | F43: Agrosistemas Sustentables | G43: CARRASCO JIMENEZ JORGE | H43: INIA | I43: Adjudicado | J43: SI | K43: APROBADO
A44: 3 | B44: 44414 | C44: FONTAGRO | D44: 16-Rayentue | E44: Agtechmetro | F44: Agrosistemas Sustentables | G44: FELMER ECHEVERRIA, SOFIA | H44: U. AUSTRAL | I44: N/A | J44: SI | K44: RECHAZADO
A45: 4 | B45: 44377 | C45: Fondecyt Regular 2022 | D45: 16-Rayentue | E45: Identification of QTLs and candidate genes associated with differential susceptibilty/resistance to bacterial canker in segragating progenies of sweet cherry (Prunus avium L.). | F45: Producción Vegetal | G45: SAGREDO DIAZ, BORIS | H45: INIA | I45: No Adjudicado | J45: SI | K45: RECHAZADO
A46: 5 | B46: 44377 | C46: Fondecyt Regular 2022 | D46: 16-Rayentue | E46: FLOWERING IN A WARM CLIMATE: EFFECT(S) OF HIGH TEMPERATURE ON FLORAL BUD DEVELOPMENT IN SWEET CHERRY TREES (Prunus avium L.) | F46: Producción Vegetal | G46: SAGREDO DIAZ, BORIS | H46: CEAF | I46: No Adjudicado | J46: SI | K46: RECHAZADO
A47: 6 | B47: 44277 | C47: Proyectos de Innovación Región de O'Higgins 2021 | D47: 16-Rayentue | E47: Manejo sustentable de agua, suelos y cultivos, para enfrentar la escasez hídrica, erosión, y consecuencias de los incendios forestales, por efecto del cambio climático, en las comunas de Pumanque, Paredones, Litueche y La Estrella. Región de O`Higgins | F47: Agrosistemas Sustentables | G47: CARRASCO JIMENEZ JORGE | H47: INIA | I47: No Postulado | J47: NO | K47: NO APLICA | L47: No alcanzo a presentar el proyecto
A48: 7 | B48: 44277 | C48: Proyectos de Innovación Región de O'Higgins 2021 | D48: 16-Rayentue | E48: Desarrollo de una aplicación online para la optimización del uso de plaguicidas en cítricos como adaptación al cambio climático para la región de O’Higgins | F48: Producción Vegetal | G48: ABARCA REYES, LUIS PATRICIO | H48: INIA | I48: No Adjudicado | J48: SI | K48: RECHAZADO
A49: 8 | B49: 44256 | C49: Concurso IDeA I+D 2021 | D49: 16-Rayentue, 20-Quilamapu | E49: Celdas Solares Flexibles a base de Silica Biogénica y Grafeno (FlexSiGraf) | F49: Producción Vegetal | G49: SAGREDO DIAZ, BORIS | H49: UA - Universidad Autónoma de Chile; UDEC - Universidad de Concepción | I49: No Adjudicado | J49: SI | K49: RECHAZADO
A50: 9 | B50: 44251 | C50: Concurso IDeA I+D 2021 | D50: 16-Rayentue, 20-Quilamapu | E50: Desarrollo y validación de una herramienta molecular para monitorear las poblaciones epifitas de Pseudomonas syringae pv syringae para optimizar el control del cáncer bacterial en cerezos | F50: Producción Vegetal | G50: SAGREDO DIAZ, BORIS | H50: INIA | I50: Perfil no Seleccionado | J50: NO | K50: RECHAZADO
A51: 10 | B51: 44245 | C51: IV Concurso Nacional de Financiamiento Basal para Centros Científicos y Tecnológicos | D51: 16-Rayentue | E51: Center on Smart Agriculture for a One Health Future | F51: Producción Vegetal | G51: SAGREDO DIAZ, BORIS | H51: UOH - Universidad de O'Higgins | I51: Perfil no Seleccionado | J51: NO | K51: RECHAZADO
A52: 1 | B52: 44111 | C52: I Concurso Nodos para la Aceleración de Impacto Territorial de la CTCI año 2020 | D52: 16-Rayentue, 20-Quilamapu | E52: Economía Circular y Sostenibilidad en los Procesos Industriales de la Macrozona Centro-Sur: Aseguramiento Agroalimentario | F52: Producción Vegetal | G52: SAGREDO DIAZ, BORIS | H52: U. Autonoma | I52: No Adjudicado | J52: SI | K52: RECHAZADO
A53: 2 | B53: 44083 | C53: Convocatoria Nacional de Proyectos 2020-2021 FIA | D53: 16-Rayentue, 20-Quilamapu | E53: Potenciamiento del cultivo de Quínoa como una alternativa productiva sustentable en la Región del Maule y valoración de la calidad nutricional de los granos | F53: Producción Vegetal | G53: ALFARO JARA, CHRISTIAN EUGENIO | H53: U Talca | I53: Rechazado | J53: NO | K53: NO APLICA
A54: 3 | B54: 44083 | C54: Convocatoria Nacional de Proyectos 2020-2021 FIA | D54: 16-Rayentue | E54: Plataforma virtual para el ajuste de parámetros operativos en pulverizadores agrícolas para la aplicación eficiente de plaguicidas en cítricos | F54: Producción Vegetal | G54: ABARCA REYES, LUIS PATRICIO | H54: INIA | I54: Perfil no Seleccionado | J54: NO | K54: NO APLICA
A55: 4 | B55: 44083 | C55: Convocatoria Nacional de Proyectos 2020-2021 FIA | D55: 16-Rayentue | E55: Elaboración y utilización de pellet a partir de lana ovina de descarte, para optimizar los recursos hídricos y mitigar el efecto del cambio climático. | F55: Agrosistemas Sustentables | G55: AGUIRRE AGUILERA, CRISTIAN | H55: INIA | I55: Perfil no Seleccionado | J55: NO | K55: NO APLICA
A56: 5 | B56: 44083 | C56: Convocatoria Nacional de Proyectos 2020-2021 FIA | D56: 16-Rayentue | E56: Desarrollo y validación de un sistema automatizado de humidificación de alta presión como una herramienta multipropósito para el cultivo del cerezo bajo macrotúneles | F56: Producción Vegetal | G56: OTAROLA ALIAGA, JAIME IGNACIO | H56: INIA | I56: No Adjudicado | J56: SI | K56: RECHAZADO | L56: Paso Admisibilidad pero no paso a 2° etapa
A57: 6 | B57: 44074 | C57: Fondecyt de Postdoctorado 2021 | D57: 16-Rayentue | E57: Determination of root traits of durum wheat (Triticum turgidum L. spp. Durum) released from 1915 to 2015 to improve wheat grain yield in the Mediterranean dry land environments. | F57: Producción Vegetal | G57: ALFARO JARA, CHRISTIAN EUGENIO | H57: INIA | I57: No Adjudicado | J57: SI | K57: RECHAZADO
A58: 7 | B58: 44048 | C58: FIC- Región del Maule | D58: 16-Rayentue, 20-Quilamapu, 21-Raihuen | E58: Transferencia en la incorporación de técnicas y tecnologías para la aplicación de fitosanitarios en cultivos de berries | F58: Producción Vegetal | G58: ABARCA REYES, LUIS PATRICIO | H58: INIA | I58: Perfil Seleccionado c/obs | J58: NO | K58: NO APLICA | L58: No realizo las correcciones a las observaciones
A59: 8 | B59: 44048 | C59: FIC- Región del Maule | D59: 16-Rayentue, 20-Quilamapu | E59: Manejo del cáncer bacterial en huertos de cerezo de la Región del Maule a través de un control ecológicamente sustentable | F59: Producción Vegetal | G59: OTAROLA ALIAGA, JAIME IGNACIO | H59: INIA | I59: No Adjudicado | J59: SI | K59: RECHAZADO
A60: 9 | B60: 43998 | C60: FIC O'Higgins 2020 | D60: 16-Rayentue | E60: Ag Tech Invest Lab Innovation | F60: Agrosistemas Sustentables | G60: FELMER ECHEVERRIA, SOFIA | H60: INIA | I60: Adjudicado | J60: SI | K60: APROBADO
A61: 10 | B61: 43992 | C61: FIC O'Higgins 2020 | D61: 16-Rayentue | E61: Transferencia hongos de la madera en frutales de carozo: situación actual y estrategias de control en la Región de O´Higgins. | F61: Producción Vegetal | G61: LEMUS SEPULVEDA, GAMALIER FDO | H61: INIA | I61: Adjudicado | J61: SI | K61: APROBADO
A62: 11 | B62: 43991 | C62: FIC O'Higgins 2020 | D62: 16-Rayentue | E62: Transferencia Manejo hídrico eficiente en frutales para nueva zona de riego | F62: Producción Vegetal | G62: OTAROLA ALIAGA, JAIME IGNACIO | H62: INIA | I62: No Adjudicado | J62: SI | K62: RECHAZADO
A63: 12 | B63: 43983 | C63: FONDECYT Regular 2021 | D63: 16-Rayentue | E63: Identification and development of molecular markers associated with genes responsible for the determination of sex in maqui (A. chilensis) and its location at chromosomal level. | F63: Producción Vegetal | G63: SAGREDO DIAZ, BORIS | H63: U. Autonoma Ch | I63: No Adjudicado | J63: SI | K63: RECHAZADO
A64: 13 | B64: 43981 | C64: FONDECYT Regular 2021 | D64: 16-Rayentue | E64: Identificación de factores genéticos y moleculares asociados a respuesta diferencial al cáncer bacterial en cerezos (Prunus avium L.) en grupos de variedades con resistencia contrastante | F64: Producción Vegetal | G64: SAGREDO DIAZ, BORIS | H64: INIA | I64: No Adjudicado | J64: SI | K64: RECHAZADO
A65: 14 | B65: 43980 | C65: FONDECYT Regular 2021 | D65: 16-Rayentue | E65: HYDRAULIC MECHANISMS AND CARBON METABOLISM IN THE ADAPTATION OF DURUM WHEAT TO CONDITIONS OF CLIMATE CHANGE | F65: Producción Vegetal | G65: ALFARO JARA, CHRISTIAN EUGENIO | H65: UCH | I65: No Adjudicado | J65: SI | K65: RECHAZADO
A66: 15 | B66: 43924 | C66: Súmate a Innovar - INNOVA-CORFO | D66: 16-Rayentue | E66: Efecto de la humidificación durante la cosecha de paltas para mejorar la condición de la fruta post-frío | F66: Producción Vegetal | G66: OTAROLA ALIAGA, JAIME IGNACIO | H66: INIA | I66: Perfil Seleccionado | J66: NO | K66: NO APLICA | L66: No se realiza postulación porque la empresa interesada no puede realizar el aporte por la situación económica causada por COVID-19
A67: 1 | B67: 43776 | C67: Anillos de Investigacion en Ciencia Y tecnolog a para la Regi n de O Higgins 2019 | D67: 16-RAYENTUE, 20-QUILAMAPU, 13-LA CRUZ | E67: Deep insight in the cherry plant defense responses tobacterial canker disease in a scenario of water restriction | F67: Producción Vegetal | G67: SAGREDO DIAZ, BORIS | H67: UOH | I67: Perfil Seleccionado | J67: SI | K67: APROBADO
A68: 2 | B68: 43776 | C68: X Concurso de Equipamiento Cientifico y Tecnologico FONDEQUIP Regi n de O Higgins a o 2019 | D68: 16-RAYENTUE, 20-QUILAMAPU, 13-LA CRUZ | E68: Desarrollo de una plataforma de análisis de fragmentos y secuencias de ADN para fortalecer el desarrollo científico y tecnológico de la Región de O Higgins | F68: Producción Vegetal | G68: SAGREDO DIAZ, BORIS | H68: INIA | I68: Perfil no Seleccionado | J68: SI | K68: APROBADO
A69: 3 | B69: 43775 | C69: X Concurso de Equipamiento Cient fico y Tecnol gico FONDEQUIP Regi n de O Higgins a o 2019 | D69: 16-Rayentue | E69: Fortalecimiento y ampliación de un laboratorio de física de suelos y riego para su consolidación en la investigación y servicios en la región de O Higgins | F69: Agrosistemas Sustentables | G69: CARRASCO JIMENEZ JORGE | H69: INIA | I69: En revisión por SubDirector Regional de I+D | J69: NO | K69: NO APLICA
A70: 4 | B70: 43731 | C70: Convocatoria Nacional Proyectos de Innovación 2019 FIA | D70: 16-Rayentue, 20-Quilamapu | E70: Bioinmunizador microbiano endófito para el manejo agroecológico de la cebolla como estrategia para disminuir el uso de agroquímicos en el cultivo. | F70: Agrosistemas Sustentables | G70: VEGA CANDIA, BARBARA CHANTAL | H70: INIA | I70: Perfil Seleccionado | J70: SI | K70: RECHAZADO | L70: NO APARECE EN LA LISTA DE PROYECTOS QUE PASARON LA 1° ETAPA
A71: 5 | B71: 43731 | C71: Convocatoria Nacional Proyectos de Innovación 2019 FIA | D71: 10-La Platina, 16-Rayentue, 20-Quilamapu, 30-Carillanca | E71: Conociendo la dinámica poblacional de Pseudomonas syringae para un control mas efectivo y sustentable del cáncer bacterial en Cerezos en Chile | F71: Producción Vegetal | G71: SAGREDO DIAZ, BORIS | H71: INIA | I71: Perfil no Seleccionado | J71: NO | K71: NO APLICA
A72: 6 | B72: 43724 | C72: Convocatoria Nacional Proyectos de Innovación 2019 FIA | D72: 16-Rayentue | E72: Manejos sustentables para enfrentar un escenario de sequía en huertos frutales | F72: Producción Vegetal | G72: OTAROLA ALIAGA, JAIME IGNACIO | H72: INIA | I72: Perfil no Seleccionado | J72: NO | K72: NO APLICA
A73: 7 | B73: 43711 | C73: VIII Concurso de Investigación Tecnológica 2019-IDeA | D73: 16-Rayentue | E73: Validación de la tecnología de nanoburbujas en distintos niveles de la cadena de producción de fruta fresca | F73: Producción Vegetal | G73: OTAROLA ALIAGA, JAIME IGNACIO | H73: INIA | I73: Perfil Seleccionado | J73: SI | K73: RECHAZADO
A74: 8 | B74: 43711 | C74: VIII Concurso de Investigación Tecnológica 2019-IDeA | D74: 10-La Platina, 16-Rayentue, 20-Quilamapu, 30-Carillanca | E74: Nuevas herramientas de monitoreo de poblaciones de Pseudomonas syringae agente causal del cáncer bacterial en cerezos para apoyar sistemas integrados de control y reducir contaminación con Cu+2. | F74: Producción Vegetal | G74: SAGREDO DIAZ, BORIS | H74: INIA | I74: Perfil Seleccionado | J74: SI | K74: RECHAZADO
A75: 9 | B75: 43711 | C75: FONDECYT DE POSTDOCTORADO 2020 | D75: 16-Rayentue, 15-Hidango, 20-Quilamapu, 14-Los Tilos | E75: DETERMINACIÓN DE LAS BASES FISIOLÓGICAS DE LA ADAPTACIÓN DE GENOTIPOS DE TRIGO CANDEAL DE INIA A CONDICIONES DE SEQUÍA EN EL SECANO MEDITERRÁNEO DE CHILE | F75: Producción Vegetal | G75: ALFARO JARA, CHRISTIAN EUGENIO | H75: INIA | I75: Perfil Seleccionado | J75: SI | K75: APROBADO
A76: 10 | B76: 43685 | C76: Bienes Públicos 2019- Temática "Adaptación al Cambio Climático" | D76: 16-Rayentue | E76: Adaptación al manejo agronómico del cultivo de cerezo desarrollado bajo cubiertas plásticas | F76: Producción Vegetal | G76: OTAROLA ALIAGA, JAIME IGNACIO | H76: INIA | I76: Perfil Seleccionado | J76: SI | K76: RECHAZADO | L76: No es pertinente
A77: 11 | B77: 43681 | C77: Bienes Públicos 2019- Temática "Adaptación al Cambio Climático" | D77: 16-Rayentue | E77: Manejo de frutales ante un escenario de sequía en la región de O’Higgins | F77: Producción Vegetal | G77: OTAROLA ALIAGA, JAIME IGNACIO | H77: INIA | I77: En revisión por SubDirector Regional de I+D | J77: NO | K77: NO APLICA
A78: 12 | B78: 43677 | C78: Bienes Públicos 2019- Temática "Adaptación al Cambio Climático" | D78: 16-Rayentue | E78: Generación de una línea base para el establecimiento frutal en el valle de Nilahue con disponibilidad de agua de riego a través del embalse Convento Viejo. | F78: Producción Vegetal | G78: OTAROLA ALIAGA, JAIME IGNACIO | H78: INIA | I78: En revisión por SubDirector Regional de I+D | J78: NO | K78: NO APLICA
A79: 13 | B79: 43642 | C79: XXIII Concurso Nacional de Proyectos Explora para elaboración de productos de divulgación de las ciencias y la tecnología 2019 2020 | D79: 16-RAYENTUE, 15-HIDANGO | E79: NATIVOAPP 2 0 Plataforma móvil y web para mapear e identificarflora nativa en Chile | F79: Producción Vegetal | G79: SAGREDO DIAZ BORIS | H79: INIA | I79: APROBADO | J79: SI | K79: RECHAZADO | L79: no adjudicar la propuesta, debido a que la solución no está debidamente identiﬁcada
A80: 14 | B80: 43628 | C80: IX Concurso de Vinculación Ciencia Empresa | D80: 16-RAYENTUE, 01-DIRECCIÓN NACIONAL | E80: Vinculación Ciencia Empresa Una Plataforma Científico Técnica para enfrentar los desafíos ante el aumento de cobertura de riego del ECV Embalse Convento Viejo en la comuna de Marchigue | F80: Producción Vegetal | G80: SAGREDO DIAZ BORIS | H80: INIA | I80: APROBADO | J80: NO | K80: NO APLICA | L80: No alcanzo a presentarlo a la FF
A81: 15 | B81: 43620 | C81: Concurso Regular Fondecyt 2020 | D81: 14-LOS TILOS, 16-RAYENTUE, 10-LA PLATINA, 05-INTIHUASI | E81: Disentangling the epigenetic influence on fruit development and ripening in three stone fruits Prunus species | F81: Producción Vegetal | G81: DONOSO CONTRERAS JOSE MANUEL | H81: U. de Chile | I81: APROBADO | J81: SI | K81: APROBADO
A82: 16 | B82: 43616 | C82: PCI ECOS CONICYT Concurso de proyectos de intercambio Chile Francia 2019 | D82: 14-LOS TILOS, 10-LA PLATINA, 16-RAYENTUE | E82: Collaborative counter season research efforts between France and Chile analysis of traits affected by climate change in sweet cherry in order to create new varieties adapted to future environmental conditions | F82: Producción Vegetal | G82: DONOSO CONTRERAS JOSE MANUEL | H82: INIA | I82: APROBADO | J82: SI | K82: RECHAZADO
A83: 17 | B83: 43493 | C83: CONCURSO IDEA I+D 2019 | D83: 16-RAYENTUE, 20-QUILAMAPU | E83: Plataforma de Información Epidemiologica para facilitar el control del Cáncer Bacterial en Cerezos | F83: Producción Vegetal | G83: SAGREDO DIAZ BORIS | H83: INIA | I83: APROBADO | J83: SI | K83: RECHAZADO
A84: 1 | B84: 2018 | C84: Concurso Postdoctorado 2019 | D84: Rayentué | E84: INTERACCIÓN G X E DE CARACTERES DE ADAPTACIÓN A CONDICIONES DE ESTRÉS HÍDRICO EN Y SU EFECTO SOBRE LA DETERMINACIÓN DEL RENDIMIENTO EN TRIGO CANDEAL | F84: Producción Vegetal | G84: ALFARO JARA CHRISTIAN EUGENIO | H84: INIA | I84: Perfil Seleccionado | J84: SI | K84: RECHAZADO
A85: 2 | B85: 2018 | C85: Concurso Regular Fondecyt 2019 | D85: Rayentué | E85: MECANISMOS HIDRAULICOS Y DE METABOLISMO DEL CARBONO EN LA ADAPTACION DEL CULTIVO DE TRIGO A CONDICIONES DE CAMBIO CLIMÁTICO EN AMBIENTES DE SEQUIA SEVERA DE TIPO MEDITERRANEO | F85: Producción Vegetal | G85: ALFARO JARA CHRISTIAN EUGENIO | H85: INIA | I85: Perfil Seleccionado | J85: NO | K85: NO APLICA
A86: 3 | B86: 2018 | C86: Septimo Concurso de Investigaci n Tecnol gica 2018 IDeA | D86: Rayentué | E86: Plataforma de Información Epidemiologica para facilitar el control del Cáncer Bacterial en Cerezos | F86: Producción Vegetal | G86: SAGREDO DIAZ BORIS | H86: INIA | I86: Perfil Seleccionado | J86: NO | K86: NO APLICA | L86: NO SE ALCANZO A POSTULAR
A87: 4 | B87: 2018 | C87: Otros Concursos de alcance nacional o regional 2018 | D87: Rayentué | E87: Identificación de marcadores moleculares asociados a la determinación del sexo en maqui A chilensis y su ubicación a nivel cromosómico | F87: Producción Vegetal | G87: SAGREDO DIAZ BORIS | H87: INIA | I87: En revisión por SubDirector Regional de I+D | J87: SI | K87: RECHAZADO
A88: 5 | B88: 2018 | C88: Otros Concursos de alcance nacional o regional 2018 | D88: Rayentué | E88: Plataforma de Información Epidemiologica para facilitar el control del Cáncer Bacterial en Cerezos | F88: Producción Vegetal | G88: SAGREDO DIAZ BORIS | H88: INIA | I88: En revisión por SubDirector Regional de I+D | J88: NO | K88: NO APLICA | L88: NO SE ALCANZO A POSTULAR
A89: 6 | B89: 2018 | C89: FIA-Convocatoria Nacional Giras Nacionales para la Innovaci n de la Peque a Agricultura 2018 | D89: Rayentué | E89: Adquisición de conocimientos en el control biológico de plagas y enfermedades en las principales hortalizas de la región de O higgins | F89: Agrosistemas Sustentables | G89: VEGA CANDIA BARBARA CHANTAL | H89: INIA | I89: Perfil Seleccionado | J89: SI | K89: RECHAZADO
A90: 7 | B90: 2018 | C90: Otros Concursos de alcance nacional o regional 2018 | D90: Rayentué | E90: Captura de conocimientos y experiencias en el manejo sustentable del cultivo del tomate | F90: Agrosistemas Sustentables | G90: VEGA CANDIA BARBARA CHANTAL | H90: INIA | I90: En corrección por Comisión de Evaluación Nacional | J90: SI | K90: RECHAZADO
